Workbook

Sheet 🏠 Home
A1: A&S Internship Program | Planning Log
A3: This is your PLANNING LOG. All completed work must also be entered in the electronic tracking form at the bottom of your Canvas course page. Set share settings to 'Anyone With the Link Can View' before submitting.
A5: THREE TYPES OF INTERNSHIP EXPERIENCES
A6: 🎓 EMBEDDED
B7: Fieldwork application assigned by the instructor to practice knowledge gained in the course. These experiences align directly to the course content and are submitted as part of the course assignment.
A8: 🔗 ALIGNED
B9: Fieldwork required as identified by the internship supervisor. These experiences connect course content to your specific school or division context and are tracked in this log.
A10: ⭐ CHOICE
B11: Interns engage in opportunities of choice, planned in addition to assigned experiences. Choice hours fill remaining competency gaps and are entered in the Choice Hours tab of this log. No activity may exceed 3 hours.
A13: HOW TO USE THIS LOG
A14: Step 1 | B14: Click the tab for the course you are enrolled in this semester (e.g., 7806, 7812).
A15: Step 2 | B15: Review the pre-filled Embedded and Aligned experiences. Enter the date, location, and your role.
A16: Step 3 | B16: The RED cell shows how many Choice hours you still need. Add your choice activities in the rows below it.
A17: Step 4 | B17: Mark ONE competency (1–6) per activity using 'X' in the competency columns.
A18: Step 5 | B18: Check the 📊 Dashboard tab to monitor your overall progress toward the 320-hour goal.
A19: Step 6 | B19: Enter all completed hours in the Canvas electronic tracking form. This log is your PLAN — Canvas is the RECORD.
A21: COURSE TABS QUICK REFERENCE | C21: 2nd Pathway Course Sequence
A22: Semester 1 | B22: 7806 – School & Community Relations | 7812 – Leading Continuous Improvement | C22: 7806 – School & Community Relations | 7812 – Leading Continuous Improvement
A23: Semester 2 | B23: 7807 – Leadership I | 7811 – Teaching & Learning | C23: 7807 – Leadership I | 7811 – Teaching & Learning
B24: 7140 -- Lead II. | 7810 – School Law | C24: 7805 – Cultivating Professional Capacity | 7810 – School Law
A25: Semester 4 | B25: 7808 – School Finance | 7805 – Cultivating Professional Capacity | C25: 7808 – School Finance | 7815 – Leadership for Diverse Learners
A26: Semester 5 | B26: 7813 – Educational Technology | 7815 – Leadership for Diverse Learners

Sheet 7806
A1: INTERNSHIP LOG | 7806 – School & Community Relations | Semester 1
A2: Name: Pat Example Placement(s): Invented Elementary | E2: Total Hours Logged | G2: =SUM(F6:F200) | H2: Remaining | J2: =(32-G2)
A3: Hours by Competency (auto-calculated from your X marks below): | G3: =SUMIF($G$6:$G$200,"X",$F$6:$F$200) | H3: =SUMIF($H$6:$H$200,"X",$F$6:$F$200) | I3: =SUMIF($I$6:$I$200,"X",$F$6:$F$200) | J3: =SUMIF($J$6:$J$200,"X",$F$6:$F$200) | K3: =SUMIF($K$6:$K$200,"X",$F$6:$F$200) | L3: =SUMIF($L$6:$L$200,"X",$F$6:$F$200) | M3: ← Competency hour totals
A5: Type | B5: Date | C5: Location | D5: Role | E5: Experience Description | F5: Hrs | G5: ① | H5: ② | I5: ③ | J5: ④ | K5: ⑤ | L5: ⑥ | M5: Evidence / Notes | N5: Site name | O5: Completed
A6: EMBEDDED | B6: 46189 | C6: Agency | D6: Participant | E6: Embedded Experience: Create a School-Community Profile: Work with school stakeholders (families, caregivers, and community members) to identify emerging trends and issues within the school community. Analyze the data collected and present findings to the school leadership team. | F6: 10 | J6: X | M6: Submit: Class Assignment | O6: Yes
A7: ALIGNED | B7: 46190 | C7: Agency | D7: Participant | E7: Aligned Experience: Interview someone from an agency concerning its relationship with schools or the school division. | F7: 5 | J7: X | M7: Submit: Competency Journal 4 | O7: Yes
A8: ALIGNED | B8: 46191 | C8: Agency | D8: Participant | E8: Aligned Experience: Conduct a Technology Audit to Assess Communication Accessibility for Stakeholders. | F8: 5 | J8: X | M8: Submit: Audit Report | O8: Yes
A9: ⭐ CHOICE HOURS — 12 hours needed this semester | E9: =IF(SUMIF(A10:A59,"CHOICE",F10:F59)>=12,"✅ Choice Hours Met!","⚠ Still need: "&(12-SUMIF(A10:A59,"CHOICE",F10:F59))&" more hours") | G9: 1. I | H9: 2. O | I9: 3. O | J9: 4. S | K9: 5. P | L9: 6. A | M9: No evidence required for choice hours
A10: CHOICE | B10: 46209 | C10: High | D10: Leader | E10: Facilitated a staff data meeting with the assistant principal and drafted a one-page summary of next steps | F10: 3 | K10: X | O10: Yes
A11: CHOICE | B11: 46212 | C11: Elementary | D11: Participant | E11: Worked with the PTA president to plan a family night and wrote a reflection on community engagement barriers | F11: 3 | J11: X | O11: Yes
A12: CHOICE | B12: 46217 | C12: Central Office | D12: Observer | E12: Observed a district budget work session and wrote notes connecting decisions to school priorities | F12: 3 | I12: X | O12: Yes
A13: CHOICE
A14: CHOICE
A15: CHOICE
A16: CHOICE
A17: CHOICE
A18: CHOICE
A19: CHOICE
A20: CHOICE
A21: CHOICE
A22: CHOICE
A23: CHOICE
A24: CHOICE
... A31: CHOICE

Sheet 7812
A1: INTERNSHIP LOG | 7812 – Leading Continuous Improvement | Semester 1
A2: Name: Pat Example Placement(s): Invented Elementary | E2: Total Hours Logged | G2: =SUM(F6:F200) | H2: Remaining | J2: =(32-G2)
A3: Hours by Competency (auto-calculated from your X marks below): | G3: =SUMIF($G$6:$G$200,"X",$F$6:$F$200) | H3: =SUMIF($H$6:$H$200,"X",$F$6:$F$200) | I3: =SUMIF($I$6:$I$200,"X",$F$6:$F$200) | J3: =SUMIF($J$6:$J$200,"X",$F$6:$F$200) | K3: =SUMIF($K$6:$K$200,"X",$F$6:$F$200) | L3: =SUMIF($L$6:$L$200,"X",$F$6:$F$200) | M3: ← Competency hour totals
A5: Type | B5: Date | C5: Location | D5: Role | E5: Experience Description | F5: Hrs | G5: ① | H5: ② | I5: ③ | J5: ④ | K5: ⑤ | L5: ⑥ | M5: Evidence / Notes | N5: Site name | O5: Completed
A6: EMBEDDED | B6: 46189 | C6: Middle | D6: Participant | E6: Embedded Experience: Continuous Improvement Semester Plan: As team leader of improvement in your school, you will prepare for a short-cycle improvement cycle targeting your selected area of instructional improvement by developing a slideshow that describes your Project Charter. | F6: 15 | H6: X | M6: Submit: Assignment | O6: Yes
A7: ALIGNED | B7: 46190 | C7: Middle | D7: Participant | E7: Aligned Experience: Obtain a copy of the School Improvement Plan for your school. Debrief with a school leader about decision-making related to the SIP. | F7: 5 | H7: X | M7: Submit: Agenda and Meeting Notes | O7: Yes
A8: ALIGNED | B8: 46191 | C8: Middle | D8: Participant | E8: Aligned Experience: Participate in discussions aimed at reaching a consensus on a school issue (e.g., grading policy, behavior support). | F8: 5 | H8: X | M8: Submit: Notes Taken from Meeting | O8: Yes
A9: ⭐ CHOICE HOURS — 7 hours needed this semester | E9: =IF(SUMIF(A10:A59,"CHOICE",F10:F59)>=7,"✅ Choice Hours Met!","⚠ Still need: "&(7-SUMIF(A10:A59,"CHOICE",F10:F59))&" more hours") | G9: 1. I | H9: 2. O | I9: 3. O | J9: 4. S | K9: 5. P | L9: 6. A | M9: No evidence required for choice hours
A10: CHOICE | B10: 46209 | C10: High | D10: Leader | E10: Led a grade-level team through an improvement-cycle review with the principal and recorded recommendations | F10: 3 | K10: X | O10: Yes
A11: CHOICE | B11: 46212 | C11: Elementary | D11: Participant | E11: Interviewed two community partners about school outreach and summarized findings for the leadership team | F11: 3 | J11: X | O11: Yes
A12: CHOICE | B12: 46217 | C12: Central Office | D12: Observer | E12: Shadowed the transportation director during bus route planning and reflected on operational tradeoffs | F12: 3 | I12: X | O12: Yes
A13: CHOICE
A14: CHOICE
A15: CHOICE
A16: CHOICE
A17: CHOICE
A18: CHOICE
A19: CHOICE
A20: CHOICE
A21: CHOICE
A22: CHOICE
A23: CHOICE
A24: CHOICE
... A31: CHOICE

Sheet 7811
A1: INTERNSHIP LOG | 7811 – Teaching & Learning | Semester 2
A2: Name: Pat Example Placement(s): Invented Elementary | E2: Total Hours Logged | G2: =SUM(F6:F200) | H2: Remaining | J2: =(32-G2)
A3: Hours by Competency (auto-calculated from your X marks below): | G3: =SUMIF($G$6:$G$200,"X",$F$6:$F$200) | H3: =SUMIF($H$6:$H$200,"X",$F$6:$F$200) | I3: =SUMIF($I$6:$I$200,"X",$F$6:$F$200) | J3: =SUMIF($J$6:$J$200,"X",$F$6:$F$200) | K3: =SUMIF($K$6:$K$200,"X",$F$6:$F$200) | L3: =SUMIF($L$6:$L$200,"X",$F$6:$F$200) | M3: ← Competency hour totals
A5: Type | B5: Date | C5: Location | D5: Role | E5: Experience Description | F5: Hrs | G5: ① | H5: ② | I5: ③ | J5: ④ | K5: ⑤ | L5: ⑥ | M5: Evidence / Notes | N5: Site name | O5: Completed
A6: EMBEDDED | C6: Main Site | E6: Embedded Experience: Observation-Feedback Experience: Practice an aspect of instructional supervision. You and your mentor will visit a classroom together to observe a teacher and provide structured feedback. | F6: 15 | G6: X | M6: Submit: Assignment
A7: ALIGNED | E7: Aligned Experience: Enhance your knowledge, understanding, and application of Virginia's school leader competencies through mentor-guided fieldwork. | F7: 5 | H7: X | M7: Submit: Competency Journal #2
A8: ALIGNED | E8: Aligned Experience: Plan and Conduct a Needs Assessment: Design a simple needs assessment to identify gaps in instructional resources or support that affect student outcomes. | F8: 5 | G8: X | M8: Submit: Needs Assessment Report
A9: ⭐ CHOICE HOURS — 7 hours needed this semester | E9: =IF(SUMIF(A10:A59,"CHOICE",F10:F59)>=7,"✅ Choice Hours Met!","⚠ Still need: "&(7-SUMIF(A10:A59,"CHOICE",F10:F59))&" more hours") | G9: 1. I | H9: 2. O | I9: 3. O | J9: 4. S | K9: 5. P | L9: 6. A | M9: No evidence required for choice hours
A10: CHOICE
A11: CHOICE
A12: CHOICE
A13: CHOICE
A14: CHOICE
A15: CHOICE
A16: CHOICE
A17: CHOICE
A18: CHOICE
A19: CHOICE
A20: CHOICE
A21: CHOICE
... A27: CHOICE

Sheet 7807
A1: INTERNSHIP LOG | 7807 – Leadership I | Semester 2
A2: Name: Pat Example Placement(s): Invented Elementary | E2: Total Hours Logged | G2: =SUM(F6:F200) | H2: Remaining | J2: =(32-G2)
A3: Hours by Competency (auto-calculated from your X marks below): | G3: =SUMIF($G$6:$G$200,"X",$F$6:$F$200) | H3: =SUMIF($H$6:$H$200,"X",$F$6:$F$200) | I3: =SUMIF($I$6:$I$200,"X",$F$6:$F$200) | J3: =SUMIF($J$6:$J$200,"X",$F$6:$F$200) | K3: =SUMIF($K$6:$K$200,"X",$F$6:$F$200) | L3: =SUMIF($L$6:$L$200,"X",$F$6:$F$200) | M3: ← Competency hour totals
A5: Type | B5: Date | C5: Location | D5: Role | E5: Experience Description | F5: Hrs | G5: ① | H5: ② | I5: ③ | J5: ④ | K5: ⑤ | L5: ⑥ | M5: Evidence / Notes | N5: Site name | O5: Completed
A6: EMBEDDED | C6: Main Site | E6: Embedded Experience: Conduct a modified 90-day inquiry cycle: Create a 90-day inquiry cycle targeting a problem of practice in your school. Analyze data, identify root causes, and develop an action plan. | F6: 25 | H6: X | M6: Submit: Class Assignment
A7: ALIGNED | E7: Aligned Experience: Reflect on a Decision with your mentor: Interns must learn to reflect on their decisions and have conversations with trusted colleagues about the decision itself and the process used in making the decision. | F7: 5 | K7: X | M7: Submit: Journal – Competency 5
A8: ⭐ CHOICE HOURS — 2 hours needed this semester | E8: =IF(SUMIF(A9:A58,"CHOICE",F9:F58)>=2,"✅ Choice Hours Met!","⚠ Still need: "&(2-SUMIF(A9:A58,"CHOICE",F9:F58))&" more hours") | G8: 1. I | H8: 2. O | I8: 3. O | J8: 4. S | K8: 5. P | L8: 6. A | M8: No evidence required for choice hours
A9: CHOICE
A10: CHOICE
A11: CHOICE
A12: CHOICE
A13: CHOICE
A14: CHOICE
A15: CHOICE
A16: CHOICE
A17: CHOICE
A18: CHOICE
A19: CHOICE
A20: CHOICE
... A28: CHOICE

Sheet 7810
A1: INTERNSHIP LOG | 7810 – School Law & Policy | Semester 3
A2: Name: Pat Example Placement(s): Invented Elementary | E2: Total Hours Logged | G2: =SUM(F6:F200) | H2: Remaining | J2: =(32-G2)
A3: Hours by Competency (auto-calculated from your X marks below): | G3: =SUMIF($G$6:$G$200,"X",$F$6:$F$200) | H3: =SUMIF($H$6:$H$200,"X",$F$6:$F$200) | I3: =SUMIF($I$6:$I$200,"X",$F$6:$F$200) | J3: =SUMIF($J$6:$J$200,"X",$F$6:$F$200) | K3: =SUMIF($K$6:$K$200,"X",$F$6:$F$200) | L3: =SUMIF($L$6:$L$200,"X",$F$6:$F$200) | M3: ← Competency hour totals
A5: Type | B5: Date | C5: Location | D5: Role | E5: Experience Description | F5: Hrs | G5: ① | H5: ② | I5: ③ | J5: ④ | K5: ⑤ | L5: ⑥ | M5: Evidence / Notes | N5: Site name | O5: Completed
A6: EMBEDDED | C6: Main Site | E6: Embedded Experience: Contemporary Issues: Planning and Debate: Select a contemporary educational law or policy issue. Research both sides, develop a position paper, and participate in a structured debate. | F6: 10 | L6: X | M6: Submit: Assignment
A7: ALIGNED | E7: Aligned Experience: Attend a School Board Meeting to Observe Policy Development: Observe how school board members discuss and vote on policy issues. | F7: 5 | L7: X | M7: Submit: Competency Journal 6
A8: ALIGNED | E8: Aligned Experience: Shadow an Administrator During a Disciplinary Hearing: Observe the processes and legal considerations involved in a student disciplinary hearing. | F8: 5 | K8: X | M8: Submit: Observation Notes
A9: ⭐ CHOICE HOURS — 12 hours needed this semester | E9: =IF(SUMIF(A10:A59,"CHOICE",F10:F59)>=12,"✅ Choice Hours Met!","⚠ Still need: "&(12-SUMIF(A10:A59,"CHOICE",F10:F59))&" more hours") | G9: 1. I | H9: 2. O | I9: 3. O | J9: 4. S | K9: 5. P | L9: 6. A | M9: No evidence required for choice hours
A10: CHOICE
A11: CHOICE
A12: CHOICE
A13: CHOICE
A14: CHOICE
A15: CHOICE
A16: CHOICE
A17: CHOICE
A18: CHOICE
A19: CHOICE
A20: CHOICE
A21: CHOICE
... A31: CHOICE

Sheet 7140
A1: INTERNSHIP LOG | 7140 – Leadership II (LEAD II) | Semester 3
A2: Name: Pat Example Placement(s): Invented Elementary | E2: Total Hours Logged | G2: =SUM(F6:F200) | H2: Remaining | J2: =(32-G2)
A3: Hours by Competency (auto-calculated from your X marks below): | G3: =SUMIF($G$6:$G$200,"X",$F$6:$F$200) | H3: =SUMIF($H$6:$H$200,"X",$F$6:$F$200) | I3: =SUMIF($I$6:$I$200,"X",$F$6:$F$200) | J3: =SUMIF($J$6:$J$200,"X",$F$6:$F$200) | K3: =SUMIF($K$6:$K$200,"X",$F$6:$F$200) | L3: =SUMIF($L$6:$L$200,"X",$F$6:$F$200) | M3: ← Competency hour totals
A5: Type | B5: Date | C5: Location | D5: Role | E5: Experience Description | F5: Hrs | G5: ① | H5: ② | I5: ③ | J5: ④ | K5: ⑤ | L5: ⑥ | M5: Evidence / Notes | N5: Site name | O5: Completed
A6: EMBEDDED | C6: Main Site | E6: Embedded Experience: Performance Assessment – Field-based Learning Application: This performance assessment is organized as a highly structured Field-based Learning Application that becomes your Field-based Learning Application Report upon its final submission. | F6: 25 | G6: X | M6: Submit: Assignment
A7: ALIGNED | E7: Aligned Experience: Serve as principal for a half/full day and/or shadow a principal noting and reflecting on all or several of the dispositions outlined in the competency components. | F7: 5 | K7: X | M7: Submit: Timeline
A8: ⭐ CHOICE HOURS — 2 hours needed this semester | E8: =IF(SUMIF(A9:A58,"CHOICE",F9:F58)>=2,"✅ Choice Hours Met!","⚠ Still need: "&(2-SUMIF(A9:A58,"CHOICE",F9:F58))&" more hours") | G8: 1. I | H8: 2. O | I8: 3. O | J8: 4. S | K8: 5. P | L8: 6. A | M8: No evidence required for choice hours
A9: CHOICE
A10: CHOICE
A11: CHOICE
A12: CHOICE
A13: CHOICE
A14: CHOICE
A15: CHOICE
A16: CHOICE
A17: CHOICE
A18: CHOICE
A19: CHOICE
A20: CHOICE
... A31: CHOICE

Sheet 7808
A1: INTERNSHIP LOG | 7808 – School Finance | Semester 4
A2: Name: Pat Example Placement(s): Invented Elementary | E2: Total Hours Logged | G2: =SUM(F6:F200) | H2: Remaining | J2: =(32-G2)
A3: Hours by Competency (auto-calculated from your X marks below): | G3: =SUMIF($G$6:$G$200,"X",$F$6:$F$200) | H3: =SUMIF($H$6:$H$200,"X",$F$6:$F$200) | I3: =SUMIF($I$6:$I$200,"X",$F$6:$F$200) | J3: =SUMIF($J$6:$J$200,"X",$F$6:$F$200) | K3: =SUMIF($K$6:$K$200,"X",$F$6:$F$200) | L3: =SUMIF($L$6:$L$200,"X",$F$6:$F$200) | M3: ← Competency hour totals
A5: Type | B5: Date | C5: Location | D5: Role | E5: Experience Description | F5: Hrs | G5: ① | H5: ② | I5: ③ | J5: ④ | K5: ⑤ | L5: ⑥ | M5: Evidence / Notes | N5: Site name | O5: Completed
A6: EMBEDDED | B6: 46279 | C6: Main Site | D6: Participant | E6: Embedded Experience: Budget Analysis Project – Case Study #4: Building a School Budget. Develop a comprehensive school budget using real-world data and present it to a mock school board. | F6: 15 | I6: X | M6: Submit: Assignment | O6: Yes
A7: ALIGNED | B7: 46293 | C7: Main Site | D7: Participant | E7: Aligned Experience: School Improvement Collaboration: Work with the school improvement team to align resources (staffing, time, materials) with student achievement goals. | F7: 5 | J7: X | M7: Submit: Resource Alignment Plan | O7: Yes
A8: ALIGNED | E8: Aligned Experience: Review programs and practices for equity, fairness, and respect, and develop recommendations for improvement. | F8: 5 | K8: X | M8: Submit: Resource Evaluation Report
A9: ⭐ CHOICE HOURS — 7 hours needed this semester | E9: =IF(SUMIF(A10:A59,"CHOICE",F10:F59)>=7,"✅ Choice Hours Met!","⚠ Still need: "&(7-SUMIF(A10:A59,"CHOICE",F10:F59))&" more hours") | G9: 1. I | H9: 2. O | I9: 3. O | J9: 4. S | K9: 5. P | L9: 6. A | M9: No evidence required for choice hours
A10: CHOICE | B10: 46300 | C10: Elementary | D10: Leader | E10: Help with budget | F10: 2 | I10: X | O10: Yes
A11: CHOICE | B11: 46303 | C11: Central Office | D11: Observer | E11: Lead a culture change initiative for the whole school with the leadership team and create an action plan | F11: 3 | K11: X | O11: Yes
A12: CHOICE | B12: 46307 | C12: Middle | D12: Participant | E12: Attended finance committee | F12: 4 | L12: X
A13: CHOICE | E13: Copy and paste choice hours here. No activity may be more than three hours
A14: CHOICE
A15: CHOICE
A16: CHOICE
A17: CHOICE
A18: CHOICE
A19: CHOICE
A20: CHOICE
A21: CHOICE
A22: CHOICE
A23: CHOICE
A24: CHOICE
A25: CHOICE
... A31: CHOICE

Sheet 7805
A1: INTERNSHIP LOG | 7805 – Cultivating Professional Capacity | Semester 4
A2: Name: Pat Example Placement(s): Invented Elementary | E2: Total Hours Logged | G2: =SUM(F6:F200) | H2: Remaining | J2: =(32-G2)
A3: Hours by Competency (auto-calculated from your X marks below): | G3: =SUMIF($G$6:$G$200,"X",$F$6:$F$200) | H3: =SUMIF($H$6:$H$200,"X",$F$6:$F$200) | I3: =SUMIF($I$6:$I$200,"X",$F$6:$F$200) | J3: =SUMIF($J$6:$J$200,"X",$F$6:$F$200) | K3: =SUMIF($K$6:$K$200,"X",$F$6:$F$200) | L3: =SUMIF($L$6:$L$200,"X",$F$6:$F$200) | M3: ← Competency hour totals
A5: Type | B5: Date | C5: Location | D5: Role | E5: Experience Description | F5: Hrs | G5: ① | H5: ② | I5: ③ | J5: ④ | K5: ⑤ | L5: ⑥ | M5: Evidence / Notes | N5: Site name | O5: Completed
A6: EMBEDDED | C6: Main Site | E6: Embedded Experience: HR Roadmap – Capacity Roadmap: A cumulative project developed throughout the course focused on building and sustaining human capital capacity in your school or division. | F6: 15 | K6: X | M6: Submit: Assignment
A7: ALIGNED | E7: Aligned Experience: Participate in/observe the hiring of a teacher, instructional coach, or school instructional support professional. | F7: 5 | I7: X | M7: Submit: Journal – Competency 3
A8: ALIGNED | E8: Aligned Experience: Interview or Shadow a Non-Instructional Leader: Interview or shadow a non-instructional leader to understand their role in supporting school operations. | F8: 5 | I8: X | M8: Submit: Interview or Observation Notes
A9: ⭐ CHOICE HOURS — 7 hours needed this semester | E9: =IF(SUMIF(A10:A59,"CHOICE",F10:F59)>=7,"✅ Choice Hours Met!","⚠ Still need: "&(7-SUMIF(A10:A59,"CHOICE",F10:F59))&" more hours") | G9: 1. I | H9: 2. O | I9: 3. O | J9: 4. S | K9: 5. P | L9: 6. A | M9: No evidence required for choice hours
A10: CHOICE
A11: CHOICE
A12: CHOICE
A13: CHOICE
A14: CHOICE
A15: CHOICE
A16: CHOICE
A17: CHOICE
A18: CHOICE
A19: CHOICE
A20: CHOICE
A21: CHOICE
... A29: CHOICE

Sheet 7813
A1: INTERNSHIP LOG | 7813 – Educational Technology | Semester 5
A2: Name: Pat Example Placement(s): Invented Elementary | E2: Total Hours Logged | G2: =SUM(F6:F200) | H2: Remaining | J2: =(32-G2)
A3: Hours by Competency (auto-calculated from your X marks below): | G3: =SUMIF($G$6:$G$200,"X",$F$6:$F$200) | H3: =SUMIF($H$6:$H$200,"X",$F$6:$F$200) | I3: =SUMIF($I$6:$I$200,"X",$F$6:$F$200) | J3: =SUMIF($J$6:$J$200,"X",$F$6:$F$200) | K3: =SUMIF($K$6:$K$200,"X",$F$6:$F$200) | L3: =SUMIF($L$6:$L$200,"X",$F$6:$F$200) | M3: ← Competency hour totals
A5: Type | B5: Date | C5: Location | D5: Role | E5: Experience Description | F5: Hrs | G5: ① | H5: ② | I5: ③ | J5: ④ | K5: ⑤ | L5: ⑥ | M5: Evidence / Notes | N5: Site name | O5: Completed
A6: EMBEDDED | B6: 46303 | C6: Main Site | D6: Participant | E6: Embedded Experience: System of Practice for the Leadership of Technology: Assess leadership practices for technology integration in your school. Develop a technology leadership action plan aligned to school improvement goals. | F6: 20 | J6: X | M6: Submit: Assignment | O6: Yes
A7: ALIGNED | B7: 46304 | C7: Main Site | D7: Participant | E7: Aligned Experience: Technology Integration: Assist in integrating technology into lesson planning and delivery by collaborating with teachers to design tech-enhanced lessons. | F7: 5 | J7: X | M7: Submit: Lesson Plans | O7: Yes
A8: ALIGNED | B8: 46305 | C8: Main Site | D8: Participant | E8: Aligned Experience: Digital Resource Audit: Conduct an audit of current technology resources available in your school and assess their alignment with instructional goals. | F8: 5 | I8: X | M8: Submit: Audit Report
A9: ⭐ CHOICE HOURS — 2 hours needed this semester | E9: =IF(SUMIF(A10:A59,"CHOICE",F10:F59)>=2,"✅ Choice Hours Met!","⚠ Still need: "&(2-SUMIF(A10:A59,"CHOICE",F10:F59))&" more hours") | G9: 1. I | H9: 2. O | I9: 3. O | J9: 4. S | K9: 5. P | L9: 6. A | M9: No evidence required for choice hours
A10: CHOICE | B10: 46346 | C10: High | D10: Participant | E10: Lead a culture change initiative for the whole school with the leadership team and create an action plan | F10: 2 | K10: X
A11: CHOICE | E11: Copy and paste choice hours here. No activity may be more than three hours
A12: CHOICE | B12: 46320 | C12: Middle | D12: Participant | E12: Instructional Technology PD: Organize and lead a professional development session on tech. (VDOE 1,3,4) | F12: 1 | G12: X
A13: CHOICE
A14: CHOICE
A15: CHOICE
A16: CHOICE
A17: CHOICE
A18: CHOICE
A19: CHOICE
A20: CHOICE
A21: CHOICE
A22: CHOICE
A23: CHOICE
A24: CHOICE
... A30: CHOICE

Sheet 7815
A1: INTERNSHIP LOG | 7815 – Leadership for Diverse Learners | Semester 5
A2: Name: Pat Example Placement(s): Invented Elementary | E2: Total Hours Logged | G2: =SUM(F6:F200) | H2: Remaining | J2: =(32-G2)
A3: Hours by Competency (auto-calculated from your X marks below): | G3: =SUMIF($G$6:$G$200,"X",$F$6:$F$200) | H3: =SUMIF($H$6:$H$200,"X",$F$6:$F$200) | I3: =SUMIF($I$6:$I$200,"X",$F$6:$F$200) | J3: =SUMIF($J$6:$J$200,"X",$F$6:$F$200) | K3: =SUMIF($K$6:$K$200,"X",$F$6:$F$200) | L3: =SUMIF($L$6:$L$200,"X",$F$6:$F$200) | M3: ← Competency hour totals
A5: Type | B5: Date | C5: Location | D5: Role | E5: Experience Description | F5: Hrs | G5: ① | H5: ② | I5: ③ | J5: ④ | K5: ⑤ | L5: ⑥ | M5: Evidence / Notes | N5: Site name | O5: Completed
A6: EMBEDDED | E6: Embedded Experience: Final Group Project on Social Justice Advocacy: This collaborative assignment asks you to develop and present an advocacy plan addressing a systemic equity issue in your school or division. | F6: 10 | L6: X | M6: Submit: Assignment
A7: ALIGNED | E7: Aligned Experience: Shadow a Special Education Leader: Shadow and interview a division or school-based special education leader to understand their role, responsibilities, and challenges. | F7: 5 | G7: X | M7: Submit: Journal – Competency 1
A8: ALIGNED | E8: Aligned Experience: Oversee or observe an IEP or RTI meeting with support from the school administrator. | F8: 5 | L8: X | M8: Submit: Meeting Observation Form
A9: ⭐ CHOICE HOURS — 12 hours needed this semester | E9: =IF(SUMIF(A10:A59,"CHOICE",F10:F59)>=12,"✅ Choice Hours Met!","⚠ Still need: "&(12-SUMIF(A10:A59,"CHOICE",F10:F59))&" more hours") | G9: 1. I | H9: 2. O | I9: 3. O | J9: 4. S | K9: 5. P | L9: 6. A | M9: No evidence required for choice hours
A10: CHOICE
A11: CHOICE
A12: CHOICE
A13: CHOICE
A14: CHOICE
A15: CHOICE
A16: CHOICE
A17: CHOICE
A18: CHOICE
A19: CHOICE
A20: CHOICE
A21: CHOICE
... A28: CHOICE

Sheet 📊 Dashboard
A1: 📊 INTERNSHIP PROGRESS DASHBOARD
A3: OVERALL HOURS PROGRESS (Goal: 320 hours across 5 semesters)
B4: Planned Hours | C4: Target Hours | D4: Remaining for CHOICE
A5: 7806 – School & Community Relations | B5: ='7806'!G2 | C5: 32 | D5: =C5-B5
A6: 7812 – Leading Continuous Improvement | B6: ='7812'!G2 | C6: 32 | D6: =C6-B6
A7: 7811 – Teaching & Learning | B7: ='7811'!G2 | C7: 32 | D7: =C7-B7
A8: 7807 – Leadership I | B8: ='7807'!G2 | C8: 32 | D8: =C8-B8
A9: 7810 – School Law & Policy | B9: ='7810'!G2 | C9: 32 | D9: =C9-B9
A10: 7140 – Leadership II (LEAD II) | B10: ='7140'!G2 | C10: 32 | D10: =C10-B10
A11: 7808 – School Finance | B11: ='7808'!G2 | C11: 32 | D11: =C11-B11
A12: 7805 – Cultivating Professional Capacity | B12: ='7805'!G2 | C12: 32 | D12: =C12-B12
A13: 7813 – Educational Technology | B13: ='7813'!G2 | C13: 32 | D13: =C13-B13
A14: 7815 – Leadership for Diverse Learners | B14: ='7815'!G2 | C14: 32 | D14: =C14-B14
A15: TOTAL | B15: =SUM(B5:B14) | C15: =SUM(C5:C14) | D15: =C15-B15
A17: HOURS BY COMPETENCY (across all courses — Choice hours only)
A18: Competency | B18: Choice Hours Logged | C18: Min Required | D18: Remaining
A19: 1. Instructional Leadership | B19: =SUMIFS('7806'!$F$6:$F$200,'7806'!$A$6:$A$200,"CHOICE",'7806'!G$6:G$200,"X")+SUMIFS('7812'!$F$6:$F$200,'7812'!$A$6:$A$200,"CHOICE",'7812'!G$6:G$200,"X")+SUMIFS('7811'!$F$6:$F$200,'7811'!$A$6:$A$200,"CHOICE",'7811'!G$6:G$200,"X")+SUMIFS('7807'!$F$6:$F$200,'7807'!$A$6:$A$200,"CHOICE",'7807'!G$6:G$200,"X")+SUMIFS('7810'!$F$6:$F$200,'7810'!$A$6:$A$200,"CHOICE",'7810'!G$6:G$200,"X")+SUMIFS('7140'!$F$6:$F$200,'7140'!$A$6:$A$200,"CHOICE",'7140'!G$6:G$200,"X")+SUMIFS('7808'!$F$6:$F$200,'7808'!$A$6:$A$200,"CHOICE",'7808'!G$6:G$200,"X")+SUMIFS('7805'!$F$6:$F$200,'7805'!$A$6:$A$200,"CHOICE",'7805'!G$6:G$200,"X")+SUMIFS('7813'!$F$6:$F$200,'7813'!$A$6:$A$200,"CHOICE",'7813'!G$6:G$200,"X")+SUMIFS('7815'!$F$6:$F$200,'7815'!$A$6:$A$200,"CHOICE",'7815'!G$6:G$200,"X") | C19: 3 | D19: =MAX(0,C19-B19)
A20: 2. Organizational Management | B20: =SUMIFS('7806'!$F$6:$F$200,'7806'!$A$6:$A$200,"CHOICE",'7806'!H$6:H$200,"X")+SUMIFS('7812'!$F$6:$F$200,'7812'!$A$6:$A$200,"CHOICE",'7812'!H$6:H$200,"X")+SUMIFS('7811'!$F$6:$F$200,'7811'!$A$6:$A$200,"CHOICE",'7811'!H$6:H$200,"X")+SUMIFS('7807'!$F$6:$F$200,'7807'!$A$6:$A$200,"CHOICE",'7807'!H$6:H$200,"X")+SUMIFS('7810'!$F$6:$F$200,'7810'!$A$6:$A$200,"CHOICE",'7810'!H$6:H$200,"X")+SUMIFS('7140'!$F$6:$F$200,'7140'!$A$6:$A$200,"CHOICE",'7140'!H$6:H$200,"X")+SUMIFS('7808'!$F$6:$F$200,'7808'!$A$6:$A$200,"CHOICE",'7808'!H$6:H$200,"X")+SUMIFS('7805'!$F$6:$F$200,'7805'!$A$6:$A$200,"CHOICE",'7805'!H$6:H$200,"X")+SUMIFS('7813'!$F$6:$F$200,'7813'!$A$6:$A$200,"CHOICE",'7813'!H$6:H$200,"X")+SUMIFS('7815'!$F$6:$F$200,'7815'!$A$6:$A$200,"CHOICE",'7815'!H$6:H$200,"X") | C20: 0 | D20: =MAX(0,C20-B20)
A21: 3. Operational Management | B21: =SUMIFS('7806'!$F$6:$F$200,'7806'!$A$6:$A$200,"CHOICE",'7806'!I$6:I$200,"X")+SUMIFS('7812'!$F$6:$F$200,'7812'!$A$6:$A$200,"CHOICE",'7812'!I$6:I$200,"X")+SUMIFS('7811'!$F$6:$F$200,'7811'!$A$6:$A$200,"CHOICE",'7811'!I$6:I$200,"X")+SUMIFS('7807'!$F$6:$F$200,'7807'!$A$6:$A$200,"CHOICE",'7807'!I$6:I$200,"X")+SUMIFS('7810'!$F$6:$F$200,'7810'!$A$6:$A$200,"CHOICE",'7810'!I$6:I$200,"X")+SUMIFS('7140'!$F$6:$F$200,'7140'!$A$6:$A$200,"CHOICE",'7140'!I$6:I$200,"X")+SUMIFS('7808'!$F$6:$F$200,'7808'!$A$6:$A$200,"CHOICE",'7808'!I$6:I$200,"X")+SUMIFS('7805'!$F$6:$F$200,'7805'!$A$6:$A$200,"CHOICE",'7805'!I$6:I$200,"X")+SUMIFS('7813'!$F$6:$F$200,'7813'!$A$6:$A$200,"CHOICE",'7813'!I$6:I$200,"X")+SUMIFS('7815'!$F$6:$F$200,'7815'!$A$6:$A$200,"CHOICE",'7815'!I$6:I$200,"X") | C21: 23 | D21: =MAX(0,C21-B21)
A22: 4. Systemic Equity & Community Engagement | B22: =SUMIFS('7806'!$F$6:$F$200,'7806'!$A$6:$A$200,"CHOICE",'7806'!J$6:J$200,"X")+SUMIFS('7812'!$F$6:$F$200,'7812'!$A$6:$A$200,"CHOICE",'7812'!J$6:J$200,"X")+SUMIFS('7811'!$F$6:$F$200,'7811'!$A$6:$A$200,"CHOICE",'7811'!J$6:J$200,"X")+SUMIFS('7807'!$F$6:$F$200,'7807'!$A$6:$A$200,"CHOICE",'7807'!J$6:J$200,"X")+SUMIFS('7810'!$F$6:$F$200,'7810'!$A$6:$A$200,"CHOICE",'7810'!J$6:J$200,"X")+SUMIFS('7140'!$F$6:$F$200,'7140'!$A$6:$A$200,"CHOICE",'7140'!J$6:J$200,"X")+SUMIFS('7808'!$F$6:$F$200,'7808'!$A$6:$A$200,"CHOICE",'7808'!J$6:J$200,"X")+SUMIFS('7805'!$F$6:$F$200,'7805'!$A$6:$A$200,"CHOICE",'7805'!J$6:J$200,"X")+SUMIFS('7813'!$F$6:$F$200,'7813'!$A$6:$A$200,"CHOICE",'7813'!J$6:J$200,"X")+SUMIFS('7815'!$F$6:$F$200,'7815'!$A$6:$A$200,"CHOICE",'7815'!J$6:J$200,"X") | C22: 4 | D22: =MAX(0,C22-B22)
A23: 5. Professionalism | B23: =SUMIFS('7806'!$F$6:$F$200,'7806'!$A$6:$A$200,"CHOICE",'7806'!K$6:K$200,"X")+SUMIFS('7812'!$F$6:$F$200,'7812'!$A$6:$A$200,"CHOICE",'7812'!K$6:K$200,"X")+SUMIFS('7811'!$F$6:$F$200,'7811'!$A$6:$A$200,"CHOICE",'7811'!K$6:K$200,"X")+SUMIFS('7807'!$F$6:$F$200,'7807'!$A$6:$A$200,"CHOICE",'7807'!K$6:K$200,"X")+SUMIFS('7810'!$F$6:$F$200,'7810'!$A$6:$A$200,"CHOICE",'7810'!K$6:K$200,"X")+SUMIFS('7140'!$F$6:$F$200,'7140'!$A$6:$A$200,"CHOICE",'7140'!K$6:K$200,"X")+SUMIFS('7808'!$F$6:$F$200,'7808'!$A$6:$A$200,"CHOICE",'7808'!K$6:K$200,"X")+SUMIFS('7805'!$F$6:$F$200,'7805'!$A$6:$A$200,"CHOICE",'7805'!K$6:K$200,"X")+SUMIFS('7813'!$F$6:$F$200,'7813'!$A$6:$A$200,"CHOICE",'7813'!K$6:K$200,"X")+SUMIFS('7815'!$F$6:$F$200,'7815'!$A$6:$A$200,"CHOICE",'7815'!K$6:K$200,"X") | C23: 23 | D23: =MAX(0,C23-B23)
A24: 6. Advocacy | B24: =SUMIFS('7806'!$F$6:$F$200,'7806'!$A$6:$A$200,"CHOICE",'7806'!L$6:L$200,"X")+SUMIFS('7812'!$F$6:$F$200,'7812'!$A$6:$A$200,"CHOICE",'7812'!L$6:L$200,"X")+SUMIFS('7811'!$F$6:$F$200,'7811'!$A$6:$A$200,"CHOICE",'7811'!L$6:L$200,"X")+SUMIFS('7807'!$F$6:$F$200,'7807'!$A$6:$A$200,"CHOICE",'7807'!L$6:L$200,"X")+SUMIFS('7810'!$F$6:$F$200,'7810'!$A$6:$A$200,"CHOICE",'7810'!L$6:L$200,"X")+SUMIFS('7140'!$F$6:$F$200,'7140'!$A$6:$A$200,"CHOICE",'7140'!L$6:L$200,"X")+SUMIFS('7808'!$F$6:$F$200,'7808'!$A$6:$A$200,"CHOICE",'7808'!L$6:L$200,"X")+SUMIFS('7805'!$F$6:$F$200,'7805'!$A$6:$A$200,"CHOICE",'7805'!L$6:L$200,"X")+SUMIFS('7813'!$F$6:$F$200,'7813'!$A$6:$A$200,"CHOICE",'7813'!L$6:L$200,"X")+SUMIFS('7815'!$F$6:$F$200,'7815'!$A$6:$A$200,"CHOICE",'7815'!L$6:L$200,"X") | C24: 17 | D24: =MAX(0,C24-B24)
A27: 📍 LOCATION REQUIREMENT: At least 50 hours must be completed outside your own building (min. 12.5 per site type)
A30: 📍 EXTERNAL HOURS TRACKER (Requirement: 50 hrs outside your building | min. 12.5 per site type)
A31: Enter your location in column C of each course tab using the dropdown. 'Main Site' = your own building and is excluded from external totals.
A32: Location Type | B32: Hours Logged | C32: Minimum Required | D32: Still Needed
A33: Elementary | B33: =IFERROR(SUMIF('7806'!C6:C200,"Elementary",('7806'!F6:F200)),0)+IFERROR(SUMIF('7812'!C6:C200,"Elementary",('7812'!F6:F200)),0)+IFERROR(SUMIF('7811'!C6:C200,"Elementary",('7811'!F6:F200)),0)+IFERROR(SUMIF('7807'!C6:C200,"Elementary",('7807'!F6:F200)),0)+IFERROR(SUMIF('7810'!C6:C200,"Elementary",('7810'!F6:F200)),0)+IFERROR(SUMIF('7140'!C6:C200,"Elementary",('7140'!F6:F200)),0)+IFERROR(SUMIF('7808'!C6:C200,"Elementary",('7808'!F6:F200)),0)+IFERROR(SUMIF('7805'!C6:C200,"Elementary",('7805'!F6:F200)),0)+IFERROR(SUMIF('7813'!C6:C200,"Elementary",('7813'!F6:F200)),0)+IFERROR(SUMIF('7815'!C6:C200,"Elementary",('7815'!F6:F200)),0) | C33: 12.5 | D33: =IF(B33>=12.5,"✅ Met","⚠ "&TEXT(MAX(0,12.5-B33),"0.0")&" hrs needed")
A34: Middle | B34: =IFERROR(SUMIF('7806'!C6:C200,"Middle",('7806'!F6:F200)),0)+IFERROR(SUMIF('7812'!C6:C200,"Middle",('7812'!F6:F200)),0)+IFERROR(SUMIF('7811'!C6:C200,"Middle",('7811'!F6:F200)),0)+IFERROR(SUMIF('7807'!C6:C200,"Middle",('7807'!F6:F200)),0)+IFERROR(SUMIF('7810'!C6:C200,"Middle",('7810'!F6:F200)),0)+IFERROR(SUMIF('7140'!C6:C200,"Middle",('7140'!F6:F200)),0)+IFERROR(SUMIF('7808'!C6:C200,"Middle",('7808'!F6:F200)),0)+IFERROR(SUMIF('7805'!C6:C200,"Middle",('7805'!F6:F200)),0)+IFERROR(SUMIF('7813'!C6:C200,"Middle",('7813'!F6:F200)),0)+IFERROR(SUMIF('7815'!C6:C200,"Middle",('7815'!F6:F200)),0) | C34: 12.5 | D34: =IF(B34>=12.5,"✅ Met","⚠ "&TEXT(MAX(0,12.5-B34),"0.0")&" hrs needed")
A35: High | B35: =IFERROR(SUMIF('7806'!C6:C200,"High",('7806'!F6:F200)),0)+IFERROR(SUMIF('7812'!C6:C200,"High",('7812'!F6:F200)),0)+IFERROR(SUMIF('7811'!C6:C200,"High",('7811'!F6:F200)),0)+IFERROR(SUMIF('7807'!C6:C200,"High",('7807'!F6:F200)),0)+IFERROR(SUMIF('7810'!C6:C200,"High",('7810'!F6:F200)),0)+IFERROR(SUMIF('7140'!C6:C200,"High",('7140'!F6:F200)),0)+IFERROR(SUMIF('7808'!C6:C200,"High",('7808'!F6:F200)),0)+IFERROR(SUMIF('7805'!C6:C200,"High",('7805'!F6:F200)),0)+IFERROR(SUMIF('7813'!C6:C200,"High",('7813'!F6:F200)),0)+IFERROR(SUMIF('7815'!C6:C200,"High",('7815'!F6:F200)),0) | C35: 12.5 | D35: =IF(B35>=12.5,"✅ Met","⚠ "&TEXT(MAX(0,12.5-B35),"0.0")&" hrs needed")
A36: Central Office | B36: =IFERROR(SUMIF('7806'!C6:C200,"Central Office",('7806'!F6:F200)),0)+IFERROR(SUMIF('7812'!C6:C200,"Central Office",('7812'!F6:F200)),0)+IFERROR(SUMIF('7811'!C6:C200,"Central Office",('7811'!F6:F200)),0)+IFERROR(SUMIF('7807'!C6:C200,"Central Office",('7807'!F6:F200)),0)+IFERROR(SUMIF('7810'!C6:C200,"Central Office",('7810'!F6:F200)),0)+IFERROR(SUMIF('7140'!C6:C200,"Central Office",('7140'!F6:F200)),0)+IFERROR(SUMIF('7808'!C6:C200,"Central Office",('7808'!F6:F200)),0)+IFERROR(SUMIF('7805'!C6:C200,"Central Office",('7805'!F6:F200)),0)+IFERROR(SUMIF('7813'!C6:C200,"Central Office",('7813'!F6:F200)),0)+IFERROR(SUMIF('7815'!C6:C200,"Central Office",('7815'!F6:F200)),0) | C36: 12.5 | D36: =IF(B36>=12.5,"✅ Met","⚠ "&TEXT(MAX(0,12.5-B36),"0.0")&" hrs needed")
A37: Agency | B37: =IFERROR(SUMIF('7806'!C6:C200,"Agency",('7806'!F6:F200)),0)+IFERROR(SUMIF('7812'!C6:C200,"Agency",('7812'!F6:F200)),0)+IFERROR(SUMIF('7811'!C6:C200,"Agency",('7811'!F6:F200)),0)+IFERROR(SUMIF('7807'!C6:C200,"Agency",('7807'!F6:F200)),0)+IFERROR(SUMIF('7810'!C6:C200,"Agency",('7810'!F6:F200)),0)+IFERROR(SUMIF('7140'!C6:C200,"Agency",('7140'!F6:F200)),0)+IFERROR(SUMIF('7808'!C6:C200,"Agency",('7808'!F6:F200)),0)+IFERROR(SUMIF('7805'!C6:C200,"Agency",('7805'!F6:F200)),0)+IFERROR(SUMIF('7813'!C6:C200,"Agency",('7813'!F6:F200)),0)+IFERROR(SUMIF('7815'!C6:C200,"Agency",('7815'!F6:F200)),0) | C37: 12.5 | D37: =IF(B37>=12.5,"✅ Met","⚠ "&TEXT(MAX(0,12.5-B37),"0.0")&" hrs needed")
A38: Other | B38: =IFERROR(SUMIF('7806'!C6:C200,"Other",('7806'!F6:F200)),0)+IFERROR(SUMIF('7812'!C6:C200,"Other",('7812'!F6:F200)),0)+IFERROR(SUMIF('7811'!C6:C200,"Other",('7811'!F6:F200)),0)+IFERROR(SUMIF('7807'!C6:C200,"Other",('7807'!F6:F200)),0)+IFERROR(SUMIF('7810'!C6:C200,"Other",('7810'!F6:F200)),0)+IFERROR(SUMIF('7140'!C6:C200,"Other",('7140'!F6:F200)),0)+IFERROR(SUMIF('7808'!C6:C200,"Other",('7808'!F6:F200)),0)+IFERROR(SUMIF('7805'!C6:C200,"Other",('7805'!F6:F200)),0)+IFERROR(SUMIF('7813'!C6:C200,"Other",('7813'!F6:F200)),0)+IFERROR(SUMIF('7815'!C6:C200,"Other",('7815'!F6:F200)),0) | C38: — | D38: —
A39: TOTAL EXTERNAL HOURS | B39: =SUM(B33:B38) | C39: 50 | D39: =IF(B39>=50,IF(COUNTIF(B33:B37,"<12.5")=0,"✅ Requirement Met!","✅ 50-hr total met, but "&COUNTIF(B33:B37,"<12.5")&" site type(s) are under 12.5 hrs"),"⚠ "&TEXT(MAX(0,50-B39),"0")&" more external hrs needed")

Sheet All CHOICE
A1: INTERN LOG: CHOICE HOURS | E1: Name: Date of Internship: Placements: | F1: Total Hours Logged | G1: =SUM(G6:G139) | H1: "SEMYR"when you add to PowerBI. I Suggest XSEMYR as you can easily cross reference the two documents by date.
A3: =MAX('CHOICE calc'!$E$2:$E$541)&" CHOICE entries found on your course tabs. A row is listed when it has a "&"description or hours."&IF(MAX('CHOICE calc'!$E$2:$E$541)>134," WARNING: only the first 134 are shown.","")
A5: Competency | B5: Date | C5: Name the Location | D5: Type | E5: Experience | F5: Role | G5: Hours | H5: Course
A6: =IFERROR(INDEX('CHOICE calc'!$F$2:$F$541,MATCH(ROWS(A$6:A6),'CHOICE calc'!$E$2:$E$541,0)),"") | B6: =IFERROR(INDEX('CHOICE calc'!$G$2:$G$541,MATCH(ROWS(A$6:A6),'CHOICE calc'!$E$2:$E$541,0)),"") | C6: =IFERROR(INDEX('CHOICE calc'!$H$2:$H$541,MATCH(ROWS(A$6:A6),'CHOICE calc'!$E$2:$E$541,0)),"") | D6: =IFERROR(INDEX('CHOICE calc'!$I$2:$I$541,MATCH(ROWS(A$6:A6),'CHOICE calc'!$E$2:$E$541,0)),"") | E6: =IFERROR(INDEX('CHOICE calc'!$J$2:$J$541,MATCH(ROWS(A$6:A6),'CHOICE calc'!$E$2:$E$541,0)),"") | F6: =IFERROR(INDEX('CHOICE calc'!$K$2:$K$541,MATCH(ROWS(A$6:A6),'CHOICE calc'!$E$2:$E$541,0)),"") | G6: =IFERROR(INDEX('CHOICE calc'!$L$2:$L$541,MATCH(ROWS(A$6:A6),'CHOICE calc'!$E$2:$E$541,0)),"") | H6: =IFERROR(INDEX('CHOICE calc'!$A$2:$A$541,MATCH(ROWS(A$6:A6),'CHOICE calc'!$E$2:$E$541,0)),"") | I6: Cumulative Totals - CHOICE HOURS
A7: =IFERROR(INDEX('CHOICE calc'!$F$2:$F$541,MATCH(ROWS(A$6:A7),'CHOICE calc'!$E$2:$E$541,0)),"") | B7: =IFERROR(INDEX('CHOICE calc'!$G$2:$G$541,MATCH(ROWS(A$6:A7),'CHOICE calc'!$E$2:$E$541,0)),"") | C7: =IFERROR(INDEX('CHOICE calc'!$H$2:$H$541,MATCH(ROWS(A$6:A7),'CHOICE calc'!$E$2:$E$541,0)),"") | D7: =IFERROR(INDEX('CHOICE calc'!$I$2:$I$541,MATCH(ROWS(A$6:A7),'CHOICE calc'!$E$2:$E$541,0)),"") | E7: =IFERROR(INDEX('CHOICE calc'!$J$2:$J$541,MATCH(ROWS(A$6:A7),'CHOICE calc'!$E$2:$E$541,0)),"") | F7: =IFERROR(INDEX('CHOICE calc'!$K$2:$K$541,MATCH(ROWS(A$6:A7),'CHOICE calc'!$E$2:$E$541,0)),"") | G7: =IFERROR(INDEX('CHOICE calc'!$L$2:$L$541,MATCH(ROWS(A$6:A7),'CHOICE calc'!$E$2:$E$541,0)),"") | H7: =IFERROR(INDEX('CHOICE calc'!$A$2:$A$541,MATCH(ROWS(A$6:A7),'CHOICE calc'!$E$2:$E$541,0)),"") | I7: Competency | J7: Total Min Req | K7: Align/ Choice Hours | L7: Remain
A8: =IFERROR(INDEX('CHOICE calc'!$F$2:$F$541,MATCH(ROWS(A$6:A8),'CHOICE calc'!$E$2:$E$541,0)),"") | B8: =IFERROR(INDEX('CHOICE calc'!$G$2:$G$541,MATCH(ROWS(A$6:A8),'CHOICE calc'!$E$2:$E$541,0)),"") | C8: =IFERROR(INDEX('CHOICE calc'!$H$2:$H$541,MATCH(ROWS(A$6:A8),'CHOICE calc'!$E$2:$E$541,0)),"") | D8: =IFERROR(INDEX('CHOICE calc'!$I$2:$I$541,MATCH(ROWS(A$6:A8),'CHOICE calc'!$E$2:$E$541,0)),"") | E8: =IFERROR(INDEX('CHOICE calc'!$J$2:$J$541,MATCH(ROWS(A$6:A8),'CHOICE calc'!$E$2:$E$541,0)),"") | F8: =IFERROR(INDEX('CHOICE calc'!$K$2:$K$541,MATCH(ROWS(A$6:A8),'CHOICE calc'!$E$2:$E$541,0)),"") | G8: =IFERROR(INDEX('CHOICE calc'!$L$2:$L$541,MATCH(ROWS(A$6:A8),'CHOICE calc'!$E$2:$E$541,0)),"") | H8: =IFERROR(INDEX('CHOICE calc'!$A$2:$A$541,MATCH(ROWS(A$6:A8),'CHOICE calc'!$E$2:$E$541,0)),"") | I8: 1. Instructional Leadership | J8: 3 | K8: ='📊 Dashboard'!B19 | L8: =J8-K8 | M8: NOTE: Column H "Total Min Requirements" shows you how many hours are left in each competency after embedded and aligned. There is some leeway here. You can go over or under a couple of hours if you want to focus in an area of development. On the Course Hours record tab, I make suggestions on which course may be aligned best for the competency. IT IS NOT REQUIRED you follow that guidance. Remember, you SHOULD turn in choice hours each semester (Aka the alignment) BUT we recognize that sometimes the experience doesn't align with what's going on in your schools and therefore, may submit another semester.
A9: =IFERROR(INDEX('CHOICE calc'!$F$2:$F$541,MATCH(ROWS(A$6:A9),'CHOICE calc'!$E$2:$E$541,0)),"") | B9: =IFERROR(INDEX('CHOICE calc'!$G$2:$G$541,MATCH(ROWS(A$6:A9),'CHOICE calc'!$E$2:$E$541,0)),"") | C9: =IFERROR(INDEX('CHOICE calc'!$H$2:$H$541,MATCH(ROWS(A$6:A9),'CHOICE calc'!$E$2:$E$541,0)),"") | D9: =IFERROR(INDEX('CHOICE calc'!$I$2:$I$541,MATCH(ROWS(A$6:A9),'CHOICE calc'!$E$2:$E$541,0)),"") | E9: =IFERROR(INDEX('CHOICE calc'!$J$2:$J$541,MATCH(ROWS(A$6:A9),'CHOICE calc'!$E$2:$E$541,0)),"") | F9: =IFERROR(INDEX('CHOICE calc'!$K$2:$K$541,MATCH(ROWS(A$6:A9),'CHOICE calc'!$E$2:$E$541,0)),"") | G9: =IFERROR(INDEX('CHOICE calc'!$L$2:$L$541,MATCH(ROWS(A$6:A9),'CHOICE calc'!$E$2:$E$541,0)),"") | H9: =IFERROR(INDEX('CHOICE calc'!$A$2:$A$541,MATCH(ROWS(A$6:A9),'CHOICE calc'!$E$2:$E$541,0)),"") | I9: 2. Oganizational Management | J9: 0 | K9: ='📊 Dashboard'!B20 | L9: 0
A10: =IFERROR(INDEX('CHOICE calc'!$F$2:$F$541,MATCH(ROWS(A$6:A10),'CHOICE calc'!$E$2:$E$541,0)),"") | B10: =IFERROR(INDEX('CHOICE calc'!$G$2:$G$541,MATCH(ROWS(A$6:A10),'CHOICE calc'!$E$2:$E$541,0)),"") | C10: =IFERROR(INDEX('CHOICE calc'!$H$2:$H$541,MATCH(ROWS(A$6:A10),'CHOICE calc'!$E$2:$E$541,0)),"") | D10: =IFERROR(INDEX('CHOICE calc'!$I$2:$I$541,MATCH(ROWS(A$6:A10),'CHOICE calc'!$E$2:$E$541,0)),"") | E10: =IFERROR(INDEX('CHOICE calc'!$J$2:$J$541,MATCH(ROWS(A$6:A10),'CHOICE calc'!$E$2:$E$541,0)),"") | F10: =IFERROR(INDEX('CHOICE calc'!$K$2:$K$541,MATCH(ROWS(A$6:A10),'CHOICE calc'!$E$2:$E$541,0)),"") | G10: =IFERROR(INDEX('CHOICE calc'!$L$2:$L$541,MATCH(ROWS(A$6:A10),'CHOICE calc'!$E$2:$E$541,0)),"") | H10: =IFERROR(INDEX('CHOICE calc'!$A$2:$A$541,MATCH(ROWS(A$6:A10),'CHOICE calc'!$E$2:$E$541,0)),"") | I10: 3. Operational Management | J10: 23 | K10: ='📊 Dashboard'!B21 | L10: =J10-K10
A11: =IFERROR(INDEX('CHOICE calc'!$F$2:$F$541,MATCH(ROWS(A$6:A11),'CHOICE calc'!$E$2:$E$541,0)),"") | B11: =IFERROR(INDEX('CHOICE calc'!$G$2:$G$541,MATCH(ROWS(A$6:A11),'CHOICE calc'!$E$2:$E$541,0)),"") | C11: =IFERROR(INDEX('CHOICE calc'!$H$2:$H$541,MATCH(ROWS(A$6:A11),'CHOICE calc'!$E$2:$E$541,0)),"") | D11: =IFERROR(INDEX('CHOICE calc'!$I$2:$I$541,MATCH(ROWS(A$6:A11),'CHOICE calc'!$E$2:$E$541,0)),"") | E11: =IFERROR(INDEX('CHOICE calc'!$J$2:$J$541,MATCH(ROWS(A$6:A11),'CHOICE calc'!$E$2:$E$541,0)),"") | F11: =IFERROR(INDEX('CHOICE calc'!$K$2:$K$541,MATCH(ROWS(A$6:A11),'CHOICE calc'!$E$2:$E$541,0)),"") | G11: =IFERROR(INDEX('CHOICE calc'!$L$2:$L$541,MATCH(ROWS(A$6:A11),'CHOICE calc'!$E$2:$E$541,0)),"") | H11: =IFERROR(INDEX('CHOICE calc'!$A$2:$A$541,MATCH(ROWS(A$6:A11),'CHOICE calc'!$E$2:$E$541,0)),"") | I11: 4. Systemic Equity and Community Engagement | J11: 4 | K11: ='📊 Dashboard'!B22 | L11: =J11-K11
A12: =IFERROR(INDEX('CHOICE calc'!$F$2:$F$541,MATCH(ROWS(A$6:A12),'CHOICE calc'!$E$2:$E$541,0)),"") | B12: =IFERROR(INDEX('CHOICE calc'!$G$2:$G$541,MATCH(ROWS(A$6:A12),'CHOICE calc'!$E$2:$E$541,0)),"") | C12: =IFERROR(INDEX('CHOICE calc'!$H$2:$H$541,MATCH(ROWS(A$6:A12),'CHOICE calc'!$E$2:$E$541,0)),"") | D12: =IFERROR(INDEX('CHOICE calc'!$I$2:$I$541,MATCH(ROWS(A$6:A12),'CHOICE calc'!$E$2:$E$541,0)),"") | E12: =IFERROR(INDEX('CHOICE calc'!$J$2:$J$541,MATCH(ROWS(A$6:A12),'CHOICE calc'!$E$2:$E$541,0)),"") | F12: =IFERROR(INDEX('CHOICE calc'!$K$2:$K$541,MATCH(ROWS(A$6:A12),'CHOICE calc'!$E$2:$E$541,0)),"") | G12: =IFERROR(INDEX('CHOICE calc'!$L$2:$L$541,MATCH(ROWS(A$6:A12),'CHOICE calc'!$E$2:$E$541,0)),"") | H12: =IFERROR(INDEX('CHOICE calc'!$A$2:$A$541,MATCH(ROWS(A$6:A12),'CHOICE calc'!$E$2:$E$541,0)),"") | I12: 5. Professionalism | J12: 23 | K12: ='📊 Dashboard'!B23 | L12: =J12-K12
A13: =IFERROR(INDEX('CHOICE calc'!$F$2:$F$541,MATCH(ROWS(A$6:A13),'CHOICE calc'!$E$2:$E$541,0)),"") | B13: =IFERROR(INDEX('CHOICE calc'!$G$2:$G$541,MATCH(ROWS(A$6:A13),'CHOICE calc'!$E$2:$E$541,0)),"") | C13: =IFERROR(INDEX('CHOICE calc'!$H$2:$H$541,MATCH(ROWS(A$6:A13),'CHOICE calc'!$E$2:$E$541,0)),"") | D13: =IFERROR(INDEX('CHOICE calc'!$I$2:$I$541,MATCH(ROWS(A$6:A13),'CHOICE calc'!$E$2:$E$541,0)),"") | E13: =IFERROR(INDEX('CHOICE calc'!$J$2:$J$541,MATCH(ROWS(A$6:A13),'CHOICE calc'!$E$2:$E$541,0)),"") | F13: =IFERROR(INDEX('CHOICE calc'!$K$2:$K$541,MATCH(ROWS(A$6:A13),'CHOICE calc'!$E$2:$E$541,0)),"") | G13: =IFERROR(INDEX('CHOICE calc'!$L$2:$L$541,MATCH(ROWS(A$6:A13),'CHOICE calc'!$E$2:$E$541,0)),"") | H13: =IFERROR(INDEX('CHOICE calc'!$A$2:$A$541,MATCH(ROWS(A$6:A13),'CHOICE calc'!$E$2:$E$541,0)),"") | I13: 6. Advocacy | J13: 17 | K13: ='📊 Dashboard'!B24 | L13: =J13-K13
A14: =IFERROR(INDEX('CHOICE calc'!$F$2:$F$541,MATCH(ROWS(A$6:A14),'CHOICE calc'!$E$2:$E$541,0)),"") | B14: =IFERROR(INDEX('CHOICE calc'!$G$2:$G$541,MATCH(ROWS(A$6:A14),'CHOICE calc'!$E$2:$E$541,0)),"") | C14: =IFERROR(INDEX('CHOICE calc'!$H$2:$H$541,MATCH(ROWS(A$6:A14),'CHOICE calc'!$E$2:$E$541,0)),"") | D14: =IFERROR(INDEX('CHOICE calc'!$I$2:$I$541,MATCH(ROWS(A$6:A14),'CHOICE calc'!$E$2:$E$541,0)),"") | E14: =IFERROR(INDEX('CHOICE calc'!$J$2:$J$541,MATCH(ROWS(A$6:A14),'CHOICE calc'!$E$2:$E$541,0)),"") | F14: =IFERROR(INDEX('CHOICE calc'!$K$2:$K$541,MATCH(ROWS(A$6:A14),'CHOICE calc'!$E$2:$E$541,0)),"") | G14: =IFERROR(INDEX('CHOICE calc'!$L$2:$L$541,MATCH(ROWS(A$6:A14),'CHOICE calc'!$E$2:$E$541,0)),"") | H14: =IFERROR(INDEX('CHOICE calc'!$A$2:$A$541,MATCH(ROWS(A$6:A14),'CHOICE calc'!$E$2:$E$541,0)),"")
A15: =IFERROR(INDEX('CHOICE calc'!$F$2:$F$541,MATCH(ROWS(A$6:A15),'CHOICE calc'!$E$2:$E$541,0)),"") | B15: =IFERROR(INDEX('CHOICE calc'!$G$2:$G$541,MATCH(ROWS(A$6:A15),'CHOICE calc'!$E$2:$E$541,0)),"") | C15: =IFERROR(INDEX('CHOICE calc'!$H$2:$H$541,MATCH(ROWS(A$6:A15),'CHOICE calc'!$E$2:$E$541,0)),"") | D15: =IFERROR(INDEX('CHOICE calc'!$I$2:$I$541,MATCH(ROWS(A$6:A15),'CHOICE calc'!$E$2:$E$541,0)),"") | E15: =IFERROR(INDEX('CHOICE calc'!$J$2:$J$541,MATCH(ROWS(A$6:A15),'CHOICE calc'!$E$2:$E$541,0)),"") | F15: =IFERROR(INDEX('CHOICE calc'!$K$2:$K$541,MATCH(ROWS(A$6:A15),'CHOICE calc'!$E$2:$E$541,0)),"") | G15: =IFERROR(INDEX('CHOICE calc'!$L$2:$L$541,MATCH(ROWS(A$6:A15),'CHOICE calc'!$E$2:$E$541,0)),"") | H15: =IFERROR(INDEX('CHOICE calc'!$A$2:$A$541,MATCH(ROWS(A$6:A15),'CHOICE calc'!$E$2:$E$541,0)),"")
A16: =IFERROR(INDEX('CHOICE calc'!$F$2:$F$541,MATCH(ROWS(A$6:A16),'CHOICE calc'!$E$2:$E$541,0)),"") | B16: =IFERROR(INDEX('CHOICE calc'!$G$2:$G$541,MATCH(ROWS(A$6:A16),'CHOICE calc'!$E$2:$E$541,0)),"") | C16: =IFERROR(INDEX('CHOICE calc'!$H$2:$H$541,MATCH(ROWS(A$6:A16),'CHOICE calc'!$E$2:$E$541,0)),"") | D16: =IFERROR(INDEX('CHOICE calc'!$I$2:$I$541,MATCH(ROWS(A$6:A16),'CHOICE calc'!$E$2:$E$541,0)),"") | E16: =IFERROR(INDEX('CHOICE calc'!$J$2:$J$541,MATCH(ROWS(A$6:A16),'CHOICE calc'!$E$2:$E$541,0)),"") | F16: =IFERROR(INDEX('CHOICE calc'!$K$2:$K$541,MATCH(ROWS(A$6:A16),'CHOICE calc'!$E$2:$E$541,0)),"") | G16: =IFERROR(INDEX('CHOICE calc'!$L$2:$L$541,MATCH(ROWS(A$6:A16),'CHOICE calc'!$E$2:$E$541,0)),"") | H16: =IFERROR(INDEX('CHOICE calc'!$A$2:$A$541,MATCH(ROWS(A$6:A16),'CHOICE calc'!$E$2:$E$541,0)),"")
A17: =IFERROR(INDEX('CHOICE calc'!$F$2:$F$541,MATCH(ROWS(A$6:A17),'CHOICE calc'!$E$2:$E$541,0)),"") | B17: =IFERROR(INDEX('CHOICE calc'!$G$2:$G$541,MATCH(ROWS(A$6:A17),'CHOICE calc'!$E$2:$E$541,0)),"") | C17: =IFERROR(INDEX('CHOICE calc'!$H$2:$H$541,MATCH(ROWS(A$6:A17),'CHOICE calc'!$E$2:$E$541,0)),"") | D17: =IFERROR(INDEX('CHOICE calc'!$I$2:$I$541,MATCH(ROWS(A$6:A17),'CHOICE calc'!$E$2:$E$541,0)),"") | E17: =IFERROR(INDEX('CHOICE calc'!$J$2:$J$541,MATCH(ROWS(A$6:A17),'CHOICE calc'!$E$2:$E$541,0)),"") | F17: =IFERROR(INDEX('CHOICE calc'!$K$2:$K$541,MATCH(ROWS(A$6:A17),'CHOICE calc'!$E$2:$E$541,0)),"") | G17: =IFERROR(INDEX('CHOICE calc'!$L$2:$L$541,MATCH(ROWS(A$6:A17),'CHOICE calc'!$E$2:$E$541,0)),"") | H17: =IFERROR(INDEX('CHOICE calc'!$A$2:$A$541,MATCH(ROWS(A$6:A17),'CHOICE calc'!$E$2:$E$541,0)),"")
A18: =IFERROR(INDEX('CHOICE calc'!$F$2:$F$541,MATCH(ROWS(A$6:A18),'CHOICE calc'!$E$2:$E$541,0)),"") | B18: =IFERROR(INDEX('CHOICE calc'!$G$2:$G$541,MATCH(ROWS(A$6:A18),'CHOICE calc'!$E$2:$E$541,0)),"") | C18: =IFERROR(INDEX('CHOICE calc'!$H$2:$H$541,MATCH(ROWS(A$6:A18),'CHOICE calc'!$E$2:$E$541,0)),"") | D18: =IFERROR(INDEX('CHOICE calc'!$I$2:$I$541,MATCH(ROWS(A$6:A18),'CHOICE calc'!$E$2:$E$541,0)),"") | E18: =IFERROR(INDEX('CHOICE calc'!$J$2:$J$541,MATCH(ROWS(A$6:A18),'CHOICE calc'!$E$2:$E$541,0)),"") | F18: =IFERROR(INDEX('CHOICE calc'!$K$2:$K$541,MATCH(ROWS(A$6:A18),'CHOICE calc'!$E$2:$E$541,0)),"") | G18: =IFERROR(INDEX('CHOICE calc'!$L$2:$L$541,MATCH(ROWS(A$6:A18),'CHOICE calc'!$E$2:$E$541,0)),"") | H18: =IFERROR(INDEX('CHOICE calc'!$A$2:$A$541,MATCH(ROWS(A$6:A18),'CHOICE calc'!$E$2:$E$541,0)),"")
A19: =IFERROR(INDEX('CHOICE calc'!$F$2:$F$541,MATCH(ROWS(A$6:A19),'CHOICE calc'!$E$2:$E$541,0)),"") | B19: =IFERROR(INDEX('CHOICE calc'!$G$2:$G$541,MATCH(ROWS(A$6:A19),'CHOICE calc'!$E$2:$E$541,0)),"") | C19: =IFERROR(INDEX('CHOICE calc'!$H$2:$H$541,MATCH(ROWS(A$6:A19),'CHOICE calc'!$E$2:$E$541,0)),"") | D19: =IFERROR(INDEX('CHOICE calc'!$I$2:$I$541,MATCH(ROWS(A$6:A19),'CHOICE calc'!$E$2:$E$541,0)),"") | E19: =IFERROR(INDEX('CHOICE calc'!$J$2:$J$541,MATCH(ROWS(A$6:A19),'CHOICE calc'!$E$2:$E$541,0)),"") | F19: =IFERROR(INDEX('CHOICE calc'!$K$2:$K$541,MATCH(ROWS(A$6:A19),'CHOICE calc'!$E$2:$E$541,0)),"") | G19: =IFERROR(INDEX('CHOICE calc'!$L$2:$L$541,MATCH(ROWS(A$6:A19),'CHOICE calc'!$E$2:$E$541,0)),"") | H19: =IFERROR(INDEX('CHOICE calc'!$A$2:$A$541,MATCH(ROWS(A$6:A19),'CHOICE calc'!$E$2:$E$541,0)),"")
A20: =IFERROR(INDEX('CHOICE calc'!$F$2:$F$541,MATCH(ROWS(A$6:A20),'CHOICE calc'!$E$2:$E$541,0)),"") | B20: =IFERROR(INDEX('CHOICE calc'!$G$2:$G$541,MATCH(ROWS(A$6:A20),'CHOICE calc'!$E$2:$E$541,0)),"") | C20: =IFERROR(INDEX('CHOICE calc'!$H$2:$H$541,MATCH(ROWS(A$6:A20),'CHOICE calc'!$E$2:$E$541,0)),"") | D20: =IFERROR(INDEX('CHOICE calc'!$I$2:$I$541,MATCH(ROWS(A$6:A20),'CHOICE calc'!$E$2:$E$541,0)),"") | E20: =IFERROR(INDEX('CHOICE calc'!$J$2:$J$541,MATCH(ROWS(A$6:A20),'CHOICE calc'!$E$2:$E$541,0)),"") | F20: =IFERROR(INDEX('CHOICE calc'!$K$2:$K$541,MATCH(ROWS(A$6:A20),'CHOICE calc'!$E$2:$E$541,0)),"") | G20: =IFERROR(INDEX('CHOICE calc'!$L$2:$L$541,MATCH(ROWS(A$6:A20),'CHOICE calc'!$E$2:$E$541,0)),"") | H20: =IFERROR(INDEX('CHOICE calc'!$A$2:$A$541,MATCH(ROWS(A$6:A20),'CHOICE calc'!$E$2:$E$541,0)),"")
A21: =IFERROR(INDEX('CHOICE calc'!$F$2:$F$541,MATCH(ROWS(A$6:A21),'CHOICE calc'!$E$2:$E$541,0)),"") | B21: =IFERROR(INDEX('CHOICE calc'!$G$2:$G$541,MATCH(ROWS(A$6:A21),'CHOICE calc'!$E$2:$E$541,0)),"") | C21: =IFERROR(INDEX('CHOICE calc'!$H$2:$H$541,MATCH(ROWS(A$6:A21),'CHOICE calc'!$E$2:$E$541,0)),"") | D21: =IFERROR(INDEX('CHOICE calc'!$I$2:$I$541,MATCH(ROWS(A$6:A21),'CHOICE calc'!$E$2:$E$541,0)),"") | E21: =IFERROR(INDEX('CHOICE calc'!$J$2:$J$541,MATCH(ROWS(A$6:A21),'CHOICE calc'!$E$2:$E$541,0)),"") | F21: =IFERROR(INDEX('CHOICE calc'!$K$2:$K$541,MATCH(ROWS(A$6:A21),'CHOICE calc'!$E$2:$E$541,0)),"") | G21: =IFERROR(INDEX('CHOICE calc'!$L$2:$L$541,MATCH(ROWS(A$6:A21),'CHOICE calc'!$E$2:$E$541,0)),"") | H21: =IFERROR(INDEX('CHOICE calc'!$A$2:$A$541,MATCH(ROWS(A$6:A21),'CHOICE calc'!$E$2:$E$541,0)),"")
A22: =IFERROR(INDEX('CHOICE calc'!$F$2:$F$541,MATCH(ROWS(A$6:A22),'CHOICE calc'!$E$2:$E$541,0)),"") | B22: =IFERROR(INDEX('CHOICE calc'!$G$2:$G$541,MATCH(ROWS(A$6:A22),'CHOICE calc'!$E$2:$E$541,0)),"") | C22: =IFERROR(INDEX('CHOICE calc'!$H$2:$H$541,MATCH(ROWS(A$6:A22),'CHOICE calc'!$E$2:$E$541,0)),"") | D22: =IFERROR(INDEX('CHOICE calc'!$I$2:$I$541,MATCH(ROWS(A$6:A22),'CHOICE calc'!$E$2:$E$541,0)),"") | E22: =IFERROR(INDEX('CHOICE calc'!$J$2:$J$541,MATCH(ROWS(A$6:A22),'CHOICE calc'!$E$2:$E$541,0)),"") | F22: =IFERROR(INDEX('CHOICE calc'!$K$2:$K$541,MATCH(ROWS(A$6:A22),'CHOICE calc'!$E$2:$E$541,0)),"") | G22: =IFERROR(INDEX('CHOICE calc'!$L$2:$L$541,MATCH(ROWS(A$6:A22),'CHOICE calc'!$E$2:$E$541,0)),"") | H22: =IFERROR(INDEX('CHOICE calc'!$A$2:$A$541,MATCH(ROWS(A$6:A22),'CHOICE calc'!$E$2:$E$541,0)),"")
A23: =IFERROR(INDEX('CHOICE calc'!$F$2:$F$541,MATCH(ROWS(A$6:A23),'CHOICE calc'!$E$2:$E$541,0)),"") | B23: =IFERROR(INDEX('CHOICE calc'!$G$2:$G$541,MATCH(ROWS(A$6:A23),'CHOICE calc'!$E$2:$E$541,0)),"") | C23: =IFERROR(INDEX('CHOICE calc'!$H$2:$H$541,MATCH(ROWS(A$6:A23),'CHOICE calc'!$E$2:$E$541,0)),"") | D23: =IFERROR(INDEX('CHOICE calc'!$I$2:$I$541,MATCH(ROWS(A$6:A23),'CHOICE calc'!$E$2:$E$541,0)),"") | E23: =IFERROR(INDEX('CHOICE calc'!$J$2:$J$541,MATCH(ROWS(A$6:A23),'CHOICE calc'!$E$2:$E$541,0)),"") | F23: =IFERROR(INDEX('CHOICE calc'!$K$2:$K$541,MATCH(ROWS(A$6:A23),'CHOICE calc'!$E$2:$E$541,0)),"") | G23: =IFERROR(INDEX('CHOICE calc'!$L$2:$L$541,MATCH(ROWS(A$6:A23),'CHOICE calc'!$E$2:$E$541,0)),"") | H23: =IFERROR(INDEX('CHOICE calc'!$A$2:$A$541,MATCH(ROWS(A$6:A23),'CHOICE calc'!$E$2:$E$541,0)),"")
A24: =IFERROR(INDEX('CHOICE calc'!$F$2:$F$541,MATCH(ROWS(A$6:A24),'CHOICE calc'!$E$2:$E$541,0)),"") | B24: =IFERROR(INDEX('CHOICE calc'!$G$2:$G$541,MATCH(ROWS(A$6:A24),'CHOICE calc'!$E$2:$E$541,0)),"") | C24: =IFERROR(INDEX('CHOICE calc'!$H$2:$H$541,MATCH(ROWS(A$6:A24),'CHOICE calc'!$E$2:$E$541,0)),"") | D24: =IFERROR(INDEX('CHOICE calc'!$I$2:$I$541,MATCH(ROWS(A$6:A24),'CHOICE calc'!$E$2:$E$541,0)),"") | E24: =IFERROR(INDEX('CHOICE calc'!$J$2:$J$541,MATCH(ROWS(A$6:A24),'CHOICE calc'!$E$2:$E$541,0)),"") | F24: =IFERROR(INDEX('CHOICE calc'!$K$2:$K$541,MATCH(ROWS(A$6:A24),'CHOICE calc'!$E$2:$E$541,0)),"") | G24: =IFERROR(INDEX('CHOICE calc'!$L$2:$L$541,MATCH(ROWS(A$6:A24),'CHOICE calc'!$E$2:$E$541,0)),"") | H24: =IFERROR(INDEX('CHOICE calc'!$A$2:$A$541,MATCH(ROWS(A$6:A24),'CHOICE calc'!$E$2:$E$541,0)),"")
A25: =IFERROR(INDEX('CHOICE calc'!$F$2:$F$541,MATCH(ROWS(A$6:A25),'CHOICE calc'!$E$2:$E$541,0)),"") | B25: =IFERROR(INDEX('CHOICE calc'!$G$2:$G$541,MATCH(ROWS(A$6:A25),'CHOICE calc'!$E$2:$E$541,0)),"") | C25: =IFERROR(INDEX('CHOICE calc'!$H$2:$H$541,MATCH(ROWS(A$6:A25),'CHOICE calc'!$E$2:$E$541,0)),"") | D25: =IFERROR(INDEX('CHOICE calc'!$I$2:$I$541,MATCH(ROWS(A$6:A25),'CHOICE calc'!$E$2:$E$541,0)),"") | E25: =IFERROR(INDEX('CHOICE calc'!$J$2:$J$541,MATCH(ROWS(A$6:A25),'CHOICE calc'!$E$2:$E$541,0)),"") | F25: =IFERROR(INDEX('CHOICE calc'!$K$2:$K$541,MATCH(ROWS(A$6:A25),'CHOICE calc'!$E$2:$E$541,0)),"") | G25: =IFERROR(INDEX('CHOICE calc'!$L$2:$L$541,MATCH(ROWS(A$6:A25),'CHOICE calc'!$E$2:$E$541,0)),"") | H25: =IFERROR(INDEX('CHOICE calc'!$A$2:$A$541,MATCH(ROWS(A$6:A25),'CHOICE calc'!$E$2:$E$541,0)),"")
... A139: =IFERROR(INDEX('CHOICE calc'!$F$2:$F$541,MATCH(ROWS(A$6:A139),'CHOICE calc'!$E$2:$E$541,0)),"") | B139: =IFERROR(INDEX('CHOICE calc'!$G$2:$G$541,MATCH(ROWS(A$6:A139),'CHOICE calc'!$E$2:$E$541,0)),"") | C139: =IFERROR(INDEX('CHOICE calc'!$H$2:$H$541,MATCH(ROWS(A$6:A139),'CHOICE calc'!$E$2:$E$541,0)),"") | D139: =IFERROR(INDEX('CHOICE calc'!$I$2:$I$541,MATCH(ROWS(A$6:A139),'CHOICE calc'!$E$2:$E$541,0)),"") | E139: =IFERROR(INDEX('CHOICE calc'!$J$2:$J$541,MATCH(ROWS(A$6:A139),'CHOICE calc'!$E$2:$E$541,0)),"") | F139: =IFERROR(INDEX('CHOICE calc'!$K$2:$K$541,MATCH(ROWS(A$6:A139),'CHOICE calc'!$E$2:$E$541,0)),"") | G139: =IFERROR(INDEX('CHOICE calc'!$L$2:$L$541,MATCH(ROWS(A$6:A139),'CHOICE calc'!$E$2:$E$541,0)),"") | H139: =IFERROR(INDEX('CHOICE calc'!$A$2:$A$541,MATCH(ROWS(A$6:A139),'CHOICE calc'!$E$2:$E$541,0)),"")

Sheet 📚 Competencies
A1: 📚 VIRGINIA SCHOOL LEADER COMPETENCIES
A2: 1. Instructional Leadership
B3: Knowledge, understanding, and application of planning, assessment, and instructional strategies that improve student achievement. Leaders facilitate the development and implementation of a shared vision for learning, promote a positive school culture, and provide coaching and feedback to teachers.
A5: 2. Organizational Management
B6: Knowledge, understanding, and application of leadership and management skills that promote student achievement. Leaders manage the organization, operations, and resources of a school in a way that promotes a safe, efficient, and effective learning environment.
A8: 3. Operational Management
B9: Knowledge, understanding, and application of management and organizational theories. Leaders manage human resources including recruitment, hiring, induction, professional development, evaluation, and dismissal of personnel in a fair, equitable, and legal manner.
A11: 4. Systemic Equity & Community Engagement
B12: Knowledge, understanding, and application of the conditions required to ensure equitable access and opportunity for all students. Leaders foster inclusive school communities by engaging families, caregivers, and community partners in meaningful and culturally responsive ways.
A14: 5. Professionalism
B15: Knowledge, understanding, and application of the conditions that lead to professional growth. Leaders demonstrate ethical behavior, model continuous learning, and create a culture of reflection and professional inquiry. They communicate effectively and build positive, collaborative relationships.
A17: 6. Advocacy
B18: Knowledge, understanding, and application of basic leadership skills to advocate for students, families, and school communities. Leaders act as advocates for equity and excellence, engage in policy processes, and champion the needs of all learners in public forums.

Sheet ⭐ Choice Library-All Aligned
A1: THIS TAB HAS BEEN UPDATED
A2: NOTE: YOU DO NOT NEED CHOICE HOURS IN EVERY COMPETENCY
A3: 1. Check your data tab and find "CHOICE". Within the BLUE table, identify where you have remaining hours. | B3: 2. Identify an experience you have or will engage in. CTL F a key word (Data, School Improvement, etc.) | C3: 3. Scroll over and copy the entry aligned to the competency you wish to include. Add to your planning log and then identify the alignment, hours, location, setting and your role. | D3: 4. Return to your data tab and if you have entered correctly, your tab should update showing you the hours reduced in the competency selected. | E3: 5. Continue adding experiences as you plan your internship. It is ok to plan ahead, but be sure to track if you've entered into PowerBI
A4: Virginia School Leader Internship – Competency Alignment Matrix
A5: Internship Experience | B5: Competency 1 Instructional Leadership | C5: Competency 2 Organizational Leadership | D5: Competency 3 Operational Management | E5: Competency 4 Systemic Equity | F5: Competency 5 Professionalism | G5: Competency 6 Advocacy
A6: Use survey data to gather input for planning | B6: Analyze survey results from teachers, students, or parents to identify instructional needs and inform school improvement planning. | C6: Use survey findings to align organizational practices with school community priorities and develop strategic improvement goals. | D6: Leverage survey data to make management decisions that improve the working and learning climate and support staff effectiveness. | E6: Gather diverse community input through surveys to identify equity gaps and emerging needs affecting underrepresented student populations. | F6: Model ethical, inclusive data practices by ensuring survey processes respect all stakeholders and reflect a commitment to fairness and equity. | G6: Use community voice data to advocate for policies and resources that address systemic needs identified through stakeholder surveys.
A7: Lead a focus group on school improvement needs | B7: Facilitate a staff focus group to identify instructional improvement priorities and align findings with school improvement planning. | C7: Lead a structured focus group to gather stakeholder input that informs strategic planning and organizational alignment with division goals. | D7: Use focus group findings to inform operational management decisions related to staffing, professional development, and resource allocation. | E7: Conduct a focus group that elevates the voices of diverse community members to surface equity-related needs and improvement priorities. | F7: Model reflective professional practice by facilitating inclusive, honest dialogue that upholds ethical standards in decision-making. | G7: Leverage focus group findings to advocate for school-level policy changes and resource investments aligned with community-identified needs.
A8: Identify community resources for diverse students | B8: Connect instructional support to community resources that address diverse student learning needs, including ELL and special education services. | C8: Build strategic partnerships with community organizations to expand the school's capacity to serve diverse populations through coordinated planning. | D8: Manage community partnerships as an operational function that supports student success, safety, and access to services. | E8: Identify and mobilize community resources specifically targeted toward underserved student populations to advance systemic equity. | F8: Demonstrate a professional commitment to equity by actively seeking partnerships that reflect fairness, care, and responsiveness to diverse student needs. | G8: Advocate for increased community support and external resources to address gaps in services for diverse and underrepresented students.
A9: Design teacher workshop on analyzing classroom data | B9: Design and facilitate a professional development workshop on analyzing classroom data to improve instructional practices and student outcomes. | C9: Lead a data-focused workshop that builds collective capacity for evidence-based decision-making and supports organizational learning goals. | D9: Develop a workshop that builds teachers' capacity to use student performance data for operational instructional planning and program refinement. | E9: Incorporate equity-focused data analysis into the workshop to help teachers identify achievement gaps and differentiate instruction for all learners. | F9: Model and promote a culture of continuous professional learning by facilitating collaborative, job-embedded data analysis professional development. | G9: Advocate for evidence-based instructional practices by equipping teachers with data literacy skills that support systemic improvement.
A10: Attend training on student rights and legal compliance | B10: Develop knowledge of legal frameworks governing student rights that directly impact instructional decisions and disciplinary practices. | C10: Use training insights to align school organizational policies and communication practices with federal and state legal requirements. | D10: Apply knowledge of student rights and legal compliance to operational management decisions, including discipline policies and due process. | E10: Examine how student rights laws (privacy, expression, discipline) protect marginalized students and advance equitable school environments. | F10: Strengthen professional knowledge of the moral and legal dimensions of decision-making by studying laws governing student rights and responsibilities. | G10: Use legal training to advocate for school policies and practices that fully uphold student rights and align with state and federal law.
A11: Lead a data analysis session with grade-level teams | B11: Facilitate collaborative grade-level data analysis to identify instructional strengths, gaps, and targeted improvement strategies. | C11: Use data review sessions with grade-level teams to build organizational capacity for evidence-based decision-making and continuous improvement. | D11: Apply data-driven decision-making processes to grade-level teams to strengthen operational alignment of instruction across the school. | E11: Embed equity analysis into data sessions to ensure grade-level teams examine outcome disparities and develop responsive interventions. | F11: Model collaborative, professionally responsible data inquiry that reflects ethical use of student information and shared accountability. | G11: Use data evidence from grade-level teams to advocate for systemic changes in curriculum, staffing, or resources to improve student outcomes.
A12: Lead a culture change initiative | B12: Connect school culture change efforts to instructional improvement goals, ensuring the initiative supports effective teaching and student learning. | C12: Lead an organizational culture change initiative that aligns staff behavior, beliefs, and practices with the school's mission and strategic goals. | D12: Manage the operational dimensions of a culture change initiative, including professional development design, scheduling, and resource coordination. | E12: Design and lead a culture change initiative that explicitly addresses systemic equity, inclusion, and belonging for all students and staff. | F12: Model ethical and moral leadership throughout a culture change initiative, demonstrating integrity, honesty, and care for all stakeholders. | G12: Advocate for systemic transformation in school culture by connecting change goals to broader educational equity and policy priorities.
A13: Analyze space and time utilization for instruction | B13: Evaluate how school scheduling and space are structured to support rigorous, differentiated instruction and maximize student learning time. | C13: Analyze facility and time utilization as an organizational resource and recommend strategic reallocations aligned with school improvement goals. | D13: Conduct a comprehensive operational review of space and time management to improve efficiency, safety, and instructional support structures. | E13: Examine how current use of space and time may create or perpetuate barriers to equitable access and learning for diverse student groups. | F13: Apply reflective professional judgment to assess whether current space and time practices align with ethical commitments to student success. | G13: Advocate for operational changes to space and time utilization that advance equitable learning opportunities and eliminate systemic barriers.
A14: Organize instructional technology professional development | B14: Lead professional development on using technology tools to enhance curriculum and instruction aligned with school improvement and student data. | C14: Organize a technology PD series that builds collective staff capacity and supports school-wide strategic goals for instructional improvement. | D14: Manage the operational coordination of a multi-session professional development initiative, including scheduling, resources, and evaluation. | E14: Design technology PD that is responsive to the diverse learning needs of faculty and ensures equitable access and participation for all staff. | F14: Model and promote a commitment to continuous professional learning by facilitating high-quality, data-informed instructional technology training. | G14: Advocate for sustainable technology integration by connecting PD outcomes to school improvement priorities and policy-aligned instructional goals.
A15: Plan multicultural night to engage families | B15: Connect multicultural night to instructional goals by using it as a platform to share school programs and support student academic identity. | C15: Plan and execute a multicultural event that advances the school's strategic goals for family engagement and community trust-building. | D15: Coordinate the operational logistics of a multicultural night, including facilities, staffing, materials, and communication with diverse families. | E15: Intentionally celebrate cultural diversity through the multicultural night to foster belonging, equity, and meaningful family-school partnerships. | F15: Model ethical and inclusive professional practice by creating a welcoming, respectful event that honors the cultural identities of all families. | G15: Advocate for the integration of family and cultural voice into school improvement planning by showcasing cultural assets and community strengths.
A16: Observe community-based events supporting families | B16: Observe community-agency collaboration to identify how external resources can inform and support student learning and school improvement efforts. | C16: Analyze how community agency partnerships function as an organizational strategy to extend school capacity and serve diverse student populations. | D16: Evaluate operational collaboration between the school and community agencies and reflect on how these partnerships support school management. | E16: Observe how community-based services address the diverse needs of underrepresented families and students in an equitable and culturally responsive way. | F16: Reflect on the ethical and professional dimensions of community engagement and the school's responsibility to connect families with needed resources. | G16: Identify how community-agency partnerships serve as a vehicle for advocacy, expanding support systems for students and families through external collaboration.
... A123: Participate in a division-level equity task force | B123: Contribute to a division-level equity task force by analyzing cross-school instructional data to identify systemic disparities and recommend equity-focused improvement strategies. | C123: Engage in a division-level organizational equity review that examines how policies, practices, and resource allocation affect diverse student populations across all schools. | D123: Apply operational equity review skills at the division level, examining how management decisions in areas like staffing, scheduling, and program access affect student equity. | E123: Lead or contribute to a cross-school equity analysis that surfaces systemic inequities and develops actionable, data-driven recommendations for division-wide policy change. | F123: Model ethical professional leadership by engaging honestly and rigorously in a division-level equity task force that requires confronting uncomfortable data and systemic realities. | G123: Advocate for systemic equity policy by using task force findings to present evidence-based recommendations to division leadership, school board, and community stakeholders.

Sheet ⭐ Choice Library-By Course if y
A1: ⭐ CHOICE HOURS SUGGESTION LIBRARY
A2: Each activity must be ≤ 3 hours. Use these suggestions or propose your own. Mark ONE competency per activity in your course tab.
A3: Course | B3: Competency Focus | C3: Suggested Choice Activity | D3: Suggested Evidence
A4: 7806 – School & Community Relations | B4: 4. Systemic Equity & Community Engagement | C4: Create/use existing survey to gather input from teachers, students, or parents on a school issue. (VDOE 4a) | D4: Reflection / notes / artifact
B5: 4. Systemic Equity & Community Engagement | C5: Observe an event during which an agency interacts with students, families, or school staff. (VDOE 4b) | D5: Reflection / notes / artifact
B6: 4. Systemic Equity & Community Engagement | C6: Extend the school profile assignment to conduct a community needs assessment. (VDOE 4c) | D6: Reflection / notes / artifact
B7: 4. Systemic Equity & Community Engagement | C7: Attend a PTO/A meeting to observe how school leaders engage with families and caregivers. (VDOE 4d) | D7: Reflection / notes / artifact
B8: 4. Systemic Equity & Community Engagement | C8: Plan or co-lead a school event involving families and community partners, then reflect on engagement strategies. (VDOE 4e) | D8: Reflection / notes / artifact
B9: 4. Systemic Equity & Community Engagement | C9: Plan and execute an event that brings together diverse families and community partners. (VDOE 4f) | D9: Reflection / notes / artifact
B10: 4. Systemic Equity & Community Engagement | C10: Develop or assess a communication plan to improve family-school communication. (VDOE 4g) | D10: Reflection / notes / artifact
B11: 4. Systemic Equity & Community Engagement | C11: Develop and implement a partnership with a local business or community organization. (VDOE 4h) | D11: Reflection / notes / artifact
B12: 4. Systemic Equity & Community Engagement | C12: Analyze community engagement trends and emerging issues affecting school-community relations. (VDOE 4i) | D12: Reflection / notes / artifact
B13: 4. Systemic Equity & Community Engagement | C13: Develop or strengthen partnerships with local community organizations. (VDOE 4j) | D13: Reflection / notes / artifact
B14: 4. Systemic Equity & Community Engagement | C14: Understand and practice essential crisis communication skills. (VDOE 4k) | D14: Reflection / notes / artifact
B15: 4. Systemic Equity & Community Engagement | C15: Develop public relations and social media strategies that engage the community. (VDOE 4l) | D15: Reflection / notes / artifact
A16: 7812 – Leading Continuous Improvement | B16: 2. Organizational Management | C16: Facilitate a Focus Group on School Improvement Needs. (VDOE 2a) | D16: Reflection / notes / artifact
B17: 2. Organizational Management | C17: Analyze School Performance Data to Identify Trends. (VDOE 2b) | D17: Reflection / notes / artifact
B18: 2. Organizational Management | C18: Develop a Change Management Plan for a School Initiative. (VDOE 2c) | D18: Reflection / notes / artifact
B19: 2. Organizational Management | C19: Collaborate on Strategic Planning for a School Goal. (VDOE 2d) | D19: Reflection / notes / artifact
B20: 2. Organizational Management | C20: Develop a Distributed Leadership Model. (VDOE 2e) | D20: Reflection / notes / artifact
B21: 2. Organizational Management | C21: Facilitate Consensus Building in a Staff Meeting. (VDOE 2f) | D21: Reflection / notes / artifact
B22: 2. Organizational Management | C22: Conduct a Data-Driven Program Evaluation. (VDOE 2g) | D22: Reflection / notes / artifact
B23: 2. Organizational Management | C23: Organize a Collaborative Planning Session for Staff. (VDOE 2h) | D23: Reflection / notes / artifact
B24: 2. Organizational Management | C24: Observe and Reflect on a Mediation Process. (VDOE 2i) | D24: Reflection / notes / artifact
B25: 2. Organizational Management | C25: Analyze and Present Data on Student Outcomes. (VDOE 2j) | D25: Reflection / notes / artifact
B26: 2. Organizational Management | C26: Lead a Continuous Improvement Team. (VDOE 2k) | D26: Reflection / notes / artifact
B27: 2. Organizational Management | C27: Assist in creating a professional development calendar. (VDOE 2l) | D27: Reflection / notes / artifact
A28: 7807 – Leadership I | B28: 2. Organizational Management | C28: Lead a Committee to Identify Community Resources for Diverse Students. (VDOE 2,3) | D28: Reflection / notes / artifact
B29: 2. Organizational Management | C29: Use Benchmark Data to Set Improvement Goals for a PLC. (VDOE 2) | D29: Reflection / notes / artifact
B30: 5. Professionalism | C30: Create a Plan to Increase Teacher Collaboration in PLCs. (VDOE 5e) | D30: Reflection / notes / artifact
B31: 3. Operational Management | C31: Observe or participate in a school or division strategic planning meeting. (VDOE 3) | D31: Reflection / notes / artifact
B32: 2. Organizational Management | C32: Observe how leadership responsibilities are distributed within a school. (VDOE 2) | D32: Reflection / notes / artifact
B33: 2. Organizational Management | C33: Participate in a PLC meeting to observe how teacher teams use data. (VDOE 2) | D33: Reflection / notes / artifact
B34: 2. Organizational Management | C34: Design and present a brief teacher workshop on analyzing classroom data. (VDOE 2) | D34: Reflection / notes / artifact
B35: 2. Organizational Management | C35: Work with a mentor to analyze school data and develop a basic action plan. (VDOE 2) | D35: Reflection / notes / artifact
B36: 5. Professionalism | C36: Lead a small group of teachers in discussing a change management topic. (VDOE 5e) | D36: Reflection / notes / artifact
B37: 1. Instructional Leadership | C37: Work with a teacher to identify a classroom improvement goal and create an action plan. (VDOE 1a) | D37: Reflection / notes / artifact
A38: 7811 – Teaching & Learning | B38: 2. Organizational Management | C38: Design and present a brief workshop for teachers on analyzing classroom data. (VDOE 2c) | D38: Reflection / notes / artifact
B39: 5. Professionalism | C39: Lead a small group of teachers in discussing a change management topic. (VDOE 5e) | D39: Reflection / notes / artifact
B40: 2. Organizational Management | C40: Observe how leadership responsibilities are distributed within a school. (VDOE 2) | D40: Reflection / notes / artifact
B41: 1. Instructional Leadership | C41: Observe a school leader as they make decisions related to curriculum. (VDOE 1j) | D41: Reflection / notes / artifact
B42: 1. Instructional Leadership | C42: Work with a teacher to identify a classroom improvement goal. (VDOE 1a) | D42: Reflection / notes / artifact
B43: 2. Organizational Management | C43: Attend staff or committee meetings where decisions require consensus. (VDOE 2) | D43: Reflection / notes / artifact
B44: 1. Instructional Leadership | C44: Collaborate on evaluating an instructional program using collected data. (VDOE 1) | D44: Reflection / notes / artifact
B45: 2. Organizational Management | C45: Work with a mentor to analyze school data and develop a basic action plan. (VDOE 2) | D45: Reflection / notes / artifact
A46: 7810 – School Law & Policy | B46: 5. Professionalism | C46: Participate in a Legal Training Session on Student Rights. (VDOE 5c) | D46: Reflection / notes / artifact
B47: 5. Professionalism | C47: Draft a Communication Plan for Legal Compliance on Student Data Privacy. (VDOE 5c,5d) | D47: Reflection / notes / artifact
B48: 5. Professionalism | C48: Facilitate a Staff Workshop on Ethical Decision-Making in Schools. (VDOE 5) | D48: Reflection / notes / artifact
B49: 5. Professionalism | C49: Review and Summarize State and Federal Policies on Special Education. (VDOE 5c, 6c) | D49: Reflection / notes / artifact
B50: 5. Professionalism | C50: Develop a Handbook for Staff on Legal and Ethical Practices. (VDOE 5c) | D50: Reflection / notes / artifact
B51: 6. Advocacy | C51: Research Educational Policy Development at the State Level. (VDOE 6) | D51: Reflection / notes / artifact
B52: 5. Professionalism | C52: Participate in a Policy Revision Committee for Student Discipline. (VDOE 5) | D52: Reflection / notes / artifact
B53: 5. Professionalism | C53: Observe and Document a Section 504 Meeting. (VDOE 5) | D53: Reflection / notes / artifact
B54: 6. Advocacy | C54: Research Historical Perspectives on Equity in Education Policy. (VDOE 6) | D54: Reflection / notes / artifact
B55: 5. Professionalism | C55: Create a Guide for Teachers on Legal Aspects of Student Confidentiality. (VDOE 5) | D55: Reflection / notes / artifact
B56: 5. Professionalism | C56: Participate in a Committee on School Safety Policies. (VDOE 5) | D56: Reflection / notes / artifact
B57: 5. Professionalism | C57: Shadow an Administrator During a Disciplinary Hearing. (VDOE 5) | D57: Reflection / notes / artifact
A58: 7140 – Leadership II (LEAD II) | B58: 1. Instructional Leadership | C58: Lead a Data Analysis Session with Grade-Level Teams. (VDOE 1d) | D58: Reflection / notes / artifact
B59: 1. Instructional Leadership | C59: Organize and Facilitate an Assessment Review Workshop. (VDOE 1) | D59: Reflection / notes / artifact
B60: 1. Instructional Leadership | C60: Support a School-Wide Improvement Initiative Based on Benchmark Data. (VDOE 1) | D60: Reflection / notes / artifact
B61: 1. Instructional Leadership | C61: Facilitate a Problem-Solving Session on Student Behavior. (VDOE 1) | D61: Reflection / notes / artifact
B62: 1. Instructional Leadership | C62: Facilitate a Grade-Level Team Meeting on Instructional Improvement. (VDOE 1) | D62: Reflection / notes / artifact
B63: 1. Instructional Leadership | C63: Conduct a Focus Group with Teachers on Assessment Needs. (VDOE 1) | D63: Reflection / notes / artifact
B64: 1. Instructional Leadership | C64: Develop a Data Dashboard for Monitoring Student Progress. (VDOE 2c, 3i) | D64: Reflection / notes / artifact
B65: 1. Instructional Leadership | C65: Participate in a Collaborative Evaluation of a School Program. (VDOE 2d,3i) | D65: Reflection / notes / artifact
B66: 2. Organizational Management | C66: Design a Communication Plan for Sharing Assessment Results. (VDOE 2) | D66: Reflection / notes / artifact
B67: 1. Instructional Leadership | C67: Work with teachers to develop and analyze various assessment tools. (VDOE 1) | D67: Reflection / notes / artifact
B68: 1. Instructional Leadership | C68: Observe/Participate in administrative meetings where they observe resolution of school-wide issues. (VDOE 1i) | D68: Reflection / notes / artifact
B69: 1. Instructional Leadership | C69: Collaborate with teachers in reviewing student data for planning. (VDOE 1) | D69: Reflection / notes / artifact
B70: 1. Instructional Leadership | C70: Collect data on attendance and tardiness to determine which students may need interventions. (VDOE 3i) | D70: Reflection / notes / artifact
A71: 7808 – School Finance | B71: 3. Operational Management | C71: Space and Time Utilization Analysis: Review how school facilities and schedules are used. (VDOE 3) | D71: Reflection / notes / artifact
B72: 2. Organizational Management | C72: Alignment: Work with school leaders to understand how financial resources are aligned to goals. (VDOE 2) | D72: Reflection / notes / artifact
B73: 2. Organizational Management | C73: Data Sources for Budget Improvement: Research and compile sources of data for budget decisions. (VDOE 2) | D73: Reflection / notes / artifact
B74: 3. Operational Management | C74: Budget Presentation Planning: Prepare and deliver a mock budget presentation to stakeholders. (VDOE 3e, 5d) | D74: Reflection / notes / artifact
B75: 3. Operational Management | C75: Accounting Systems and Audit Observation: Shadow the school bookkeeper. (VDOE 3) | D75: Reflection / notes / artifact
B76: 3. Operational Management | C76: Implementation Analysis Project: Meet with the school division finance office. (VDOE 3) | D76: Reflection / notes / artifact
B77: 5. Professionalism | C77: Review of School Mission and Vision with Stakeholder Group. (VDOE 5) | D77: Reflection / notes / artifact
B78: 3. Operational Management | C78: Fiscal Management Review and Budget Proposal: Shadow the division CFO. (VDOE 3) | D78: Reflection / notes / artifact
B79: 3. Operational Management | C79: Meet with the PTA treasurer and school leader to gather info on PTA budget. (VDOE 3) | D79: Reflection / notes / artifact
B80: 2. Organizational Management | C80: Analyzing and Implementing Collective Bargaining Provisions. (VDOE 2,3) | D80: Reflection / notes / artifact
B81: 3. Operational Management | C81: School Business Management: Participate in planning and organizing the school budget. (VDOE 3) | D81: Reflection / notes / artifact
B82: 2. Organizational Management | C82: Facilitate Consensus Building in a Staff Meeting. (VDOE 2) | D82: Reflection / notes / artifact
A83: 7805 – Curriculum, Program & Coaching | B83: 3. Operational Management | C83: Culture Change Initiative: Lead an initiative aimed at enhancing school culture. (VDOE 3) | D83: Reflection / notes / artifact
B84: 5. Professionalism | C84: Innovation in Instruction Project: Design and lead a project for instructional innovation. (VDOE 5) | D84: Reflection / notes / artifact
B85: 5. Professionalism | C85: Policy Review and Impact Analysis: Work with a school administrator to review a policy. (VDOE 5) | D85: Reflection / notes / artifact
B86: 3. Operational Management | C86: Professional Development Planning Committee: Participate on a committee for PD activities. (VDOE 3c, 5e) | D86: Reflection / notes / artifact
B87: 3. Operational Management | C87: Curriculum Review Committee Shadowing: Shadow an administrator on a curriculum committee. (VDOE 3) | D87: Reflection / notes / artifact
B88: 3. Operational Management | C88: Mock Interview Panel Facilitation: Organize and lead mock interview panels. (VDOE 3) | D88: Reflection / notes / artifact
B89: 3. Operational Management | C89: Recruitment Strategy Review Committee: Join or assist a committee on recruitment. (VDOE 3) | D89: Reflection / notes / artifact
B90: 3. Operational Management | C90: Peer Led Instructional Rounds: Organize and lead instructional rounds. (VDOE 3c, 5e) | D90: Reflection / notes / artifact
B91: 3. Operational Management | C91: Crisis Management Committee Participation. (VDOE 3) | D91: Reflection / notes / artifact
B92: 5. Professionalism | C92: Develop a Reflection Protocol for Teachers After Professional Learning Sessions. (VDOE 5e) | D92: Reflection / notes / artifact
A93: 7813 – Educational Technology | B93: 1. Instructional Leadership | C93: Instructional Technology PD: Organize and lead a professional development session on tech. (VDOE 1,3,4) | D93: Reflection / notes / artifact
B94: 4. Systemic Equity & Community Engagement | C94: Parent Tech Engagement Initiative: Develop and lead an initiative for parent tech literacy. (VDOE 4) | D94: Reflection / notes / artifact
B95: 3. Operational Management | C95: Leaders' Integration of Technology: Shadow a school leader integrating technology. (VDOE 3) | D95: Reflection / notes / artifact
B96: 3. Operational Management | C96: Change Management Plan for Tech Integration: Develop and implement a change management plan. (VDOE 3) | D96: Reflection / notes / artifact
B97: 3. Operational Management | C97: Data Dashboard Implementation Project: Work with school leaders to implement a data dashboard. (VDOE 3) | D97: Reflection / notes / artifact
B98: 1. Instructional Leadership | C98: Digital Instructional Strategy Development: Partner with a teacher to develop strategies. (VDOE 1) | D98: Reflection / notes / artifact
B99: 1. Instructional Leadership | C99: Collaborative Curriculum Review: Work with a grade level or dept on curriculum alignment. (VDOE 1) | D99: Reflection / notes / artifact
B100: 3. Operational Management | C100: Technology Training for Administrative Staff: Plan and implement a training session. (VDOE 3) | D100: Reflection / notes / artifact
...

Sheet 📓 Journals
A1: 📓 COMPETENCY JOURNALS — Course & Submission Reference
A3: Competency | B3: Course | C3: Journal Activity
A4: Competency 1 – Instructional Leadership | B4: 7815 | C4: Journal 1 – Shadow a Special Education Leader
A5: Competency 2 – Organizational Management | B5: 7811 | C5: Journal 2 – Enhance knowledge of VA competencies
A6: Competency 3 – Operational Management | B6: 7805 | C6: Journal 3 – HR Roadmap aligned experience
A7: Competency 4 – Systemic Equity | B7: 7806 | C7: Journal 4 – Agency/community interview
A8: Competency 5 – Professionalism | B8: 7807 | C8: Journal 5 – Decision reflection with mentor
A9: Competency 6 – Advocacy | B9: 7810 | C9: Journal 6 – School board meeting observation

Sheet CHOICE calc
A1: Course | B1: Tab | C1: Row | D1: Entry? | E1: Seq | F1: Competency | G1: Date | H1: Site name | I1: Site type | J1: Experience | K1: Role | L1: Hours | N1: Helper sheet for All CHOICE: one row per possible CHOICE row on the course tabs. A row counts as an entry when it has a description or hours. Do not edit.
A2: 7806 – School & Community Relations | B2: 7806 | C2: 6 | D2: =IF(AND(UPPER(TRIM('7806'!A6))="CHOICE",LEN(TRIM('7806'!E6&'7806'!F6))>0),1,0) | E2: =IF(D2=1,MAX(E$1:E1)+1,"") | F2: =IF(D2=1,IFERROR(CHOOSE(MATCH("X",'7806'!G6:L6,0),"①","②","③","④","⑤","⑥"),""),"") | G2: =IF(D2=1,IF('7806'!B6="","",'7806'!B6),"") | H2: =IF(D2=1,'7806'!N6&"","") | I2: =IF(D2=1,'7806'!C6&"","") | J2: =IF(D2=1,'7806'!E6&"","") | K2: =IF(D2=1,'7806'!D6&"","") | L2: =IF(D2=1,IF('7806'!F6="","",'7806'!F6),"")
A3: 7806 – School & Community Relations | B3: 7806 | C3: 7 | D3: =IF(AND(UPPER(TRIM('7806'!A7))="CHOICE",LEN(TRIM('7806'!E7&'7806'!F7))>0),1,0) | E3: =IF(D3=1,MAX(E$1:E2)+1,"") | F3: =IF(D3=1,IFERROR(CHOOSE(MATCH("X",'7806'!G7:L7,0),"①","②","③","④","⑤","⑥"),""),"") | G3: =IF(D3=1,IF('7806'!B7="","",'7806'!B7),"") | H3: =IF(D3=1,'7806'!N7&"","") | I3: =IF(D3=1,'7806'!C7&"","") | J3: =IF(D3=1,'7806'!E7&"","") | K3: =IF(D3=1,'7806'!D7&"","") | L3: =IF(D3=1,IF('7806'!F7="","",'7806'!F7),"")
A4: 7806 – School & Community Relations | B4: 7806 | C4: 8 | D4: =IF(AND(UPPER(TRIM('7806'!A8))="CHOICE",LEN(TRIM('7806'!E8&'7806'!F8))>0),1,0) | E4: =IF(D4=1,MAX(E$1:E3)+1,"") | F4: =IF(D4=1,IFERROR(CHOOSE(MATCH("X",'7806'!G8:L8,0),"①","②","③","④","⑤","⑥"),""),"") | G4: =IF(D4=1,IF('7806'!B8="","",'7806'!B8),"") | H4: =IF(D4=1,'7806'!N8&"","") | I4: =IF(D4=1,'7806'!C8&"","") | J4: =IF(D4=1,'7806'!E8&"","") | K4: =IF(D4=1,'7806'!D8&"","") | L4: =IF(D4=1,IF('7806'!F8="","",'7806'!F8),"")
A5: 7806 – School & Community Relations | B5: 7806 | C5: 9 | D5: =IF(AND(UPPER(TRIM('7806'!A9))="CHOICE",LEN(TRIM('7806'!E9&'7806'!F9))>0),1,0) | E5: =IF(D5=1,MAX(E$1:E4)+1,"") | F5: =IF(D5=1,IFERROR(CHOOSE(MATCH("X",'7806'!G9:L9,0),"①","②","③","④","⑤","⑥"),""),"") | G5: =IF(D5=1,IF('7806'!B9="","",'7806'!B9),"") | H5: =IF(D5=1,'7806'!N9&"","") | I5: =IF(D5=1,'7806'!C9&"","") | J5: =IF(D5=1,'7806'!E9&"","") | K5: =IF(D5=1,'7806'!D9&"","") | L5: =IF(D5=1,IF('7806'!F9="","",'7806'!F9),"")
A6: 7806 – School & Community Relations | B6: 7806 | C6: 10 | D6: =IF(AND(UPPER(TRIM('7806'!A10))="CHOICE",LEN(TRIM('7806'!E10&'7806'!F10))>0),1,0) | E6: =IF(D6=1,MAX(E$1:E5)+1,"") | F6: =IF(D6=1,IFERROR(CHOOSE(MATCH("X",'7806'!G10:L10,0),"①","②","③","④","⑤","⑥"),""),"") | G6: =IF(D6=1,IF('7806'!B10="","",'7806'!B10),"") | H6: =IF(D6=1,'7806'!N10&"","") | I6: =IF(D6=1,'7806'!C10&"","") | J6: =IF(D6=1,'7806'!E10&"","") | K6: =IF(D6=1,'7806'!D10&"","") | L6: =IF(D6=1,IF('7806'!F10="","",'7806'!F10),"")
A7: 7806 – School & Community Relations | B7: 7806 | C7: 11 | D7: =IF(AND(UPPER(TRIM('7806'!A11))="CHOICE",LEN(TRIM('7806'!E11&'7806'!F11))>0),1,0) | E7: =IF(D7=1,MAX(E$1:E6)+1,"") | F7: =IF(D7=1,IFERROR(CHOOSE(MATCH("X",'7806'!G11:L11,0),"①","②","③","④","⑤","⑥"),""),"") | G7: =IF(D7=1,IF('7806'!B11="","",'7806'!B11),"") | H7: =IF(D7=1,'7806'!N11&"","") | I7: =IF(D7=1,'7806'!C11&"","") | J7: =IF(D7=1,'7806'!E11&"","") | K7: =IF(D7=1,'7806'!D11&"","") | L7: =IF(D7=1,IF('7806'!F11="","",'7806'!F11),"")
A8: 7806 – School & Community Relations | B8: 7806 | C8: 12 | D8: =IF(AND(UPPER(TRIM('7806'!A12))="CHOICE",LEN(TRIM('7806'!E12&'7806'!F12))>0),1,0) | E8: =IF(D8=1,MAX(E$1:E7)+1,"") | F8: =IF(D8=1,IFERROR(CHOOSE(MATCH("X",'7806'!G12:L12,0),"①","②","③","④","⑤","⑥"),""),"") | G8: =IF(D8=1,IF('7806'!B12="","",'7806'!B12),"") | H8: =IF(D8=1,'7806'!N12&"","") | I8: =IF(D8=1,'7806'!C12&"","") | J8: =IF(D8=1,'7806'!E12&"","") | K8: =IF(D8=1,'7806'!D12&"","") | L8: =IF(D8=1,IF('7806'!F12="","",'7806'!F12),"")
A9: 7806 – School & Community Relations | B9: 7806 | C9: 13 | D9: =IF(AND(UPPER(TRIM('7806'!A13))="CHOICE",LEN(TRIM('7806'!E13&'7806'!F13))>0),1,0) | E9: =IF(D9=1,MAX(E$1:E8)+1,"") | F9: =IF(D9=1,IFERROR(CHOOSE(MATCH("X",'7806'!G13:L13,0),"①","②","③","④","⑤","⑥"),""),"") | G9: =IF(D9=1,IF('7806'!B13="","",'7806'!B13),"") | H9: =IF(D9=1,'7806'!N13&"","") | I9: =IF(D9=1,'7806'!C13&"","") | J9: =IF(D9=1,'7806'!E13&"","") | K9: =IF(D9=1,'7806'!D13&"","") | L9: =IF(D9=1,IF('7806'!F13="","",'7806'!F13),"")
A10: 7806 – School & Community Relations | B10: 7806 | C10: 14 | D10: =IF(AND(UPPER(TRIM('7806'!A14))="CHOICE",LEN(TRIM('7806'!E14&'7806'!F14))>0),1,0) | E10: =IF(D10=1,MAX(E$1:E9)+1,"") | F10: =IF(D10=1,IFERROR(CHOOSE(MATCH("X",'7806'!G14:L14,0),"①","②","③","④","⑤","⑥"),""),"") | G10: =IF(D10=1,IF('7806'!B14="","",'7806'!B14),"") | H10: =IF(D10=1,'7806'!N14&"","") | I10: =IF(D10=1,'7806'!C14&"","") | J10: =IF(D10=1,'7806'!E14&"","") | K10: =IF(D10=1,'7806'!D14&"","") | L10: =IF(D10=1,IF('7806'!F14="","",'7806'!F14),"")
A11: 7806 – School & Community Relations | B11: 7806 | C11: 15 | D11: =IF(AND(UPPER(TRIM('7806'!A15))="CHOICE",LEN(TRIM('7806'!E15&'7806'!F15))>0),1,0) | E11: =IF(D11=1,MAX(E$1:E10)+1,"") | F11: =IF(D11=1,IFERROR(CHOOSE(MATCH("X",'7806'!G15:L15,0),"①","②","③","④","⑤","⑥"),""),"") | G11: =IF(D11=1,IF('7806'!B15="","",'7806'!B15),"") | H11: =IF(D11=1,'7806'!N15&"","") | I11: =IF(D11=1,'7806'!C15&"","") | J11: =IF(D11=1,'7806'!E15&"","") | K11: =IF(D11=1,'7806'!D15&"","") | L11: =IF(D11=1,IF('7806'!F15="","",'7806'!F15),"")
A12: 7806 – School & Community Relations | B12: 7806 | C12: 16 | D12: =IF(AND(UPPER(TRIM('7806'!A16))="CHOICE",LEN(TRIM('7806'!E16&'7806'!F16))>0),1,0) | E12: =IF(D12=1,MAX(E$1:E11)+1,"") | F12: =IF(D12=1,IFERROR(CHOOSE(MATCH("X",'7806'!G16:L16,0),"①","②","③","④","⑤","⑥"),""),"") | G12: =IF(D12=1,IF('7806'!B16="","",'7806'!B16),"") | H12: =IF(D12=1,'7806'!N16&"","") | I12: =IF(D12=1,'7806'!C16&"","") | J12: =IF(D12=1,'7806'!E16&"","") | K12: =IF(D12=1,'7806'!D16&"","") | L12: =IF(D12=1,IF('7806'!F16="","",'7806'!F16),"")
A13: 7806 – School & Community Relations | B13: 7806 | C13: 17 | D13: =IF(AND(UPPER(TRIM('7806'!A17))="CHOICE",LEN(TRIM('7806'!E17&'7806'!F17))>0),1,0) | E13: =IF(D13=1,MAX(E$1:E12)+1,"") | F13: =IF(D13=1,IFERROR(CHOOSE(MATCH("X",'7806'!G17:L17,0),"①","②","③","④","⑤","⑥"),""),"") | G13: =IF(D13=1,IF('7806'!B17="","",'7806'!B17),"") | H13: =IF(D13=1,'7806'!N17&"","") | I13: =IF(D13=1,'7806'!C17&"","") | J13: =IF(D13=1,'7806'!E17&"","") | K13: =IF(D13=1,'7806'!D17&"","") | L13: =IF(D13=1,IF('7806'!F17="","",'7806'!F17),"")
... A55: 7806 – School & Community Relations | B55: 7806 | C55: 59 | D55: =IF(AND(UPPER(TRIM('7806'!A59))="CHOICE",LEN(TRIM('7806'!E59&'7806'!F59))>0),1,0) | E55: =IF(D55=1,MAX(E$1:E54)+1,"") | F55: =IF(D55=1,IFERROR(CHOOSE(MATCH("X",'7806'!G59:L59,0),"①","②","③","④","⑤","⑥"),""),"") | G55: =IF(D55=1,IF('7806'!B59="","",'7806'!B59),"") | H55: =IF(D55=1,'7806'!N59&"","") | I55: =IF(D55=1,'7806'!C59&"","") | J55: =IF(D55=1,'7806'!E59&"","") | K55: =IF(D55=1,'7806'!D59&"","") | L55: =IF(D55=1,IF('7806'!F59="","",'7806'!F59),"")
A56: 7812 – Leading Continuous Improvement | B56: 7812 | C56: 6 | D56: =IF(AND(UPPER(TRIM('7812'!A6))="CHOICE",LEN(TRIM('7812'!E6&'7812'!F6))>0),1,0) | E56: =IF(D56=1,MAX(E$1:E55)+1,"") | F56: =IF(D56=1,IFERROR(CHOOSE(MATCH("X",'7812'!G6:L6,0),"①","②","③","④","⑤","⑥"),""),"") | G56: =IF(D56=1,IF('7812'!B6="","",'7812'!B6),"") | H56: =IF(D56=1,'7812'!N6&"","") | I56: =IF(D56=1,'7812'!C6&"","") | J56: =IF(D56=1,'7812'!E6&"","") | K56: =IF(D56=1,'7812'!D6&"","") | L56: =IF(D56=1,IF('7812'!F6="","",'7812'!F6),"")
A57: 7812 – Leading Continuous Improvement | B57: 7812 | C57: 7 | D57: =IF(AND(UPPER(TRIM('7812'!A7))="CHOICE",LEN(TRIM('7812'!E7&'7812'!F7))>0),1,0) | E57: =IF(D57=1,MAX(E$1:E56)+1,"") | F57: =IF(D57=1,IFERROR(CHOOSE(MATCH("X",'7812'!G7:L7,0),"①","②","③","④","⑤","⑥"),""),"") | G57: =IF(D57=1,IF('7812'!B7="","",'7812'!B7),"") | H57: =IF(D57=1,'7812'!N7&"","") | I57: =IF(D57=1,'7812'!C7&"","") | J57: =IF(D57=1,'7812'!E7&"","") | K57: =IF(D57=1,'7812'!D7&"","") | L57: =IF(D57=1,IF('7812'!F7="","",'7812'!F7),"")
A58: 7812 – Leading Continuous Improvement | B58: 7812 | C58: 8 | D58: =IF(AND(UPPER(TRIM('7812'!A8))="CHOICE",LEN(TRIM('7812'!E8&'7812'!F8))>0),1,0) | E58: =IF(D58=1,MAX(E$1:E57)+1,"") | F58: =IF(D58=1,IFERROR(CHOOSE(MATCH("X",'7812'!G8:L8,0),"①","②","③","④","⑤","⑥"),""),"") | G58: =IF(D58=1,IF('7812'!B8="","",'7812'!B8),"") | H58: =IF(D58=1,'7812'!N8&"","") | I58: =IF(D58=1,'7812'!C8&"","") | J58: =IF(D58=1,'7812'!E8&"","") | K58: =IF(D58=1,'7812'!D8&"","") | L58: =IF(D58=1,IF('7812'!F8="","",'7812'!F8),"")
A59: 7812 – Leading Continuous Improvement | B59: 7812 | C59: 9 | D59: =IF(AND(UPPER(TRIM('7812'!A9))="CHOICE",LEN(TRIM('7812'!E9&'7812'!F9))>0),1,0) | E59: =IF(D59=1,MAX(E$1:E58)+1,"") | F59: =IF(D59=1,IFERROR(CHOOSE(MATCH("X",'7812'!G9:L9,0),"①","②","③","④","⑤","⑥"),""),"") | G59: =IF(D59=1,IF('7812'!B9="","",'7812'!B9),"") | H59: =IF(D59=1,'7812'!N9&"","") | I59: =IF(D59=1,'7812'!C9&"","") | J59: =IF(D59=1,'7812'!E9&"","") | K59: =IF(D59=1,'7812'!D9&"","") | L59: =IF(D59=1,IF('7812'!F9="","",'7812'!F9),"")
A60: 7812 – Leading Continuous Improvement | B60: 7812 | C60: 10 | D60: =IF(AND(UPPER(TRIM('7812'!A10))="CHOICE",LEN(TRIM('7812'!E10&'7812'!F10))>0),1,0) | E60: =IF(D60=1,MAX(E$1:E59)+1,"") | F60: =IF(D60=1,IFERROR(CHOOSE(MATCH("X",'7812'!G10:L10,0),"①","②","③","④","⑤","⑥"),""),"") | G60: =IF(D60=1,IF('7812'!B10="","",'7812'!B10),"") | H60: =IF(D60=1,'7812'!N10&"","") | I60: =IF(D60=1,'7812'!C10&"","") | J60: =IF(D60=1,'7812'!E10&"","") | K60: =IF(D60=1,'7812'!D10&"","") | L60: =IF(D60=1,IF('7812'!F10="","",'7812'!F10),"")
A61: 7812 – Leading Continuous Improvement | B61: 7812 | C61: 11 | D61: =IF(AND(UPPER(TRIM('7812'!A11))="CHOICE",LEN(TRIM('7812'!E11&'7812'!F11))>0),1,0) | E61: =IF(D61=1,MAX(E$1:E60)+1,"") | F61: =IF(D61=1,IFERROR(CHOOSE(MATCH("X",'7812'!G11:L11,0),"①","②","③","④","⑤","⑥"),""),"") | G61: =IF(D61=1,IF('7812'!B11="","",'7812'!B11),"") | H61: =IF(D61=1,'7812'!N11&"","") | I61: =IF(D61=1,'7812'!C11&"","") | J61: =IF(D61=1,'7812'!E11&"","") | K61: =IF(D61=1,'7812'!D11&"","") | L61: =IF(D61=1,IF('7812'!F11="","",'7812'!F11),"")
A62: 7812 – Leading Continuous Improvement | B62: 7812 | C62: 12 | D62: =IF(AND(UPPER(TRIM('7812'!A12))="CHOICE",LEN(TRIM('7812'!E12&'7812'!F12))>0),1,0) | E62: =IF(D62=1,MAX(E$1:E61)+1,"") | F62: =IF(D62=1,IFERROR(CHOOSE(MATCH("X",'7812'!G12:L12,0),"①","②","③","④","⑤","⑥"),""),"") | G62: =IF(D62=1,IF('7812'!B12="","",'7812'!B12),"") | H62: =IF(D62=1,'7812'!N12&"","") | I62: =IF(D62=1,'7812'!C12&"","") | J62: =IF(D62=1,'7812'!E12&"","") | K62: =IF(D62=1,'7812'!D12&"","") | L62: =IF(D62=1,IF('7812'!F12="","",'7812'!F12),"")
A63: 7812 – Leading Continuous Improvement | B63: 7812 | C63: 13 | D63: =IF(AND(UPPER(TRIM('7812'!A13))="CHOICE",LEN(TRIM('7812'!E13&'7812'!F13))>0),1,0) | E63: =IF(D63=1,MAX(E$1:E62)+1,"") | F63: =IF(D63=1,IFERROR(CHOOSE(MATCH("X",'7812'!G13:L13,0),"①","②","③","④","⑤","⑥"),""),"") | G63: =IF(D63=1,IF('7812'!B13="","",'7812'!B13),"") | H63: =IF(D63=1,'7812'!N13&"","") | I63: =IF(D63=1,'7812'!C13&"","") | J63: =IF(D63=1,'7812'!E13&"","") | K63: =IF(D63=1,'7812'!D13&"","") | L63: =IF(D63=1,IF('7812'!F13="","",'7812'!F13),"")
A64: 7812 – Leading Continuous Improvement | B64: 7812 | C64: 14 | D64: =IF(AND(UPPER(TRIM('7812'!A14))="CHOICE",LEN(TRIM('7812'!E14&'7812'!F14))>0),1,0) | E64: =IF(D64=1,MAX(E$1:E63)+1,"") | F64: =IF(D64=1,IFERROR(CHOOSE(MATCH("X",'7812'!G14:L14,0),"①","②","③","④","⑤","⑥"),""),"") | G64: =IF(D64=1,IF('7812'!B14="","",'7812'!B14),"") | H64: =IF(D64=1,'7812'!N14&"","") | I64: =IF(D64=1,'7812'!C14&"","") | J64: =IF(D64=1,'7812'!E14&"","") | K64: =IF(D64=1,'7812'!D14&"","") | L64: =IF(D64=1,IF('7812'!F14="","",'7812'!F14),"")
A65: 7812 – Leading Continuous Improvement | B65: 7812 | C65: 15 | D65: =IF(AND(UPPER(TRIM('7812'!A15))="CHOICE",LEN(TRIM('7812'!E15&'7812'!F15))>0),1,0) | E65: =IF(D65=1,MAX(E$1:E64)+1,"") | F65: =IF(D65=1,IFERROR(CHOOSE(MATCH("X",'7812'!G15:L15,0),"①","②","③","④","⑤","⑥"),""),"") | G65: =IF(D65=1,IF('7812'!B15="","",'7812'!B15),"") | H65: =IF(D65=1,'7812'!N15&"","") | I65: =IF(D65=1,'7812'!C15&"","") | J65: =IF(D65=1,'7812'!E15&"","") | K65: =IF(D65=1,'7812'!D15&"","") | L65: =IF(D65=1,IF('7812'!F15="","",'7812'!F15),"")
A66: 7812 – Leading Continuous Improvement | B66: 7812 | C66: 16 | D66: =IF(AND(UPPER(TRIM('7812'!A16))="CHOICE",LEN(TRIM('7812'!E16&'7812'!F16))>0),1,0) | E66: =IF(D66=1,MAX(E$1:E65)+1,"") | F66: =IF(D66=1,IFERROR(CHOOSE(MATCH("X",'7812'!G16:L16,0),"①","②","③","④","⑤","⑥"),""),"") | G66: =IF(D66=1,IF('7812'!B16="","",'7812'!B16),"") | H66: =IF(D66=1,'7812'!N16&"","") | I66: =IF(D66=1,'7812'!C16&"","") | J66: =IF(D66=1,'7812'!E16&"","") | K66: =IF(D66=1,'7812'!D16&"","") | L66: =IF(D66=1,IF('7812'!F16="","",'7812'!F16),"")
A67: 7812 – Leading Continuous Improvement | B67: 7812 | C67: 17 | D67: =IF(AND(UPPER(TRIM('7812'!A17))="CHOICE",LEN(TRIM('7812'!E17&'7812'!F17))>0),1,0) | E67: =IF(D67=1,MAX(E$1:E66)+1,"") | F67: =IF(D67=1,IFERROR(CHOOSE(MATCH("X",'7812'!G17:L17,0),"①","②","③","④","⑤","⑥"),""),"") | G67: =IF(D67=1,IF('7812'!B17="","",'7812'!B17),"") | H67: =IF(D67=1,'7812'!N17&"","") | I67: =IF(D67=1,'7812'!C17&"","") | J67: =IF(D67=1,'7812'!E17&"","") | K67: =IF(D67=1,'7812'!D17&"","") | L67: =IF(D67=1,IF('7812'!F17="","",'7812'!F17),"")
... A109: 7812 – Leading Continuous Improvement | B109: 7812 | C109: 59 | D109: =IF(AND(UPPER(TRIM('7812'!A59))="CHOICE",LEN(TRIM('7812'!E59&'7812'!F59))>0),1,0) | E109: =IF(D109=1,MAX(E$1:E108)+1,"") | F109: =IF(D109=1,IFERROR(CHOOSE(MATCH("X",'7812'!G59:L59,0),"①","②","③","④","⑤","⑥"),""),"") | G109: =IF(D109=1,IF('7812'!B59="","",'7812'!B59),"") | H109: =IF(D109=1,'7812'!N59&"","") | I109: =IF(D109=1,'7812'!C59&"","") | J109: =IF(D109=1,'7812'!E59&"","") | K109: =IF(D109=1,'7812'!D59&"","") | L109: =IF(D109=1,IF('7812'!F59="","",'7812'!F59),"")
A110: 7811 – Teaching & Learning | B110: 7811 | C110: 6 | D110: =IF(AND(UPPER(TRIM('7811'!A6))="CHOICE",LEN(TRIM('7811'!E6&'7811'!F6))>0),1,0) | E110: =IF(D110=1,MAX(E$1:E109)+1,"") | F110: =IF(D110=1,IFERROR(CHOOSE(MATCH("X",'7811'!G6:L6,0),"①","②","③","④","⑤","⑥"),""),"") | G110: =IF(D110=1,IF('7811'!B6="","",'7811'!B6),"") | H110: =IF(D110=1,'7811'!N6&"","") | I110: =IF(D110=1,'7811'!C6&"","") | J110: =IF(D110=1,'7811'!E6&"","") | K110: =IF(D110=1,'7811'!D6&"","") | L110: =IF(D110=1,IF('7811'!F6="","",'7811'!F6),"")
A111: 7811 – Teaching & Learning | B111: 7811 | C111: 7 | D111: =IF(AND(UPPER(TRIM('7811'!A7))="CHOICE",LEN(TRIM('7811'!E7&'7811'!F7))>0),1,0) | E111: =IF(D111=1,MAX(E$1:E110)+1,"") | F111: =IF(D111=1,IFERROR(CHOOSE(MATCH("X",'7811'!G7:L7,0),"①","②","③","④","⑤","⑥"),""),"") | G111: =IF(D111=1,IF('7811'!B7="","",'7811'!B7),"") | H111: =IF(D111=1,'7811'!N7&"","") | I111: =IF(D111=1,'7811'!C7&"","") | J111: =IF(D111=1,'7811'!E7&"","") | K111: =IF(D111=1,'7811'!D7&"","") | L111: =IF(D111=1,IF('7811'!F7="","",'7811'!F7),"")
A112: 7811 – Teaching & Learning | B112: 7811 | C112: 8 | D112: =IF(AND(UPPER(TRIM('7811'!A8))="CHOICE",LEN(TRIM('7811'!E8&'7811'!F8))>0),1,0) | E112: =IF(D112=1,MAX(E$1:E111)+1,"") | F112: =IF(D112=1,IFERROR(CHOOSE(MATCH("X",'7811'!G8:L8,0),"①","②","③","④","⑤","⑥"),""),"") | G112: =IF(D112=1,IF('7811'!B8="","",'7811'!B8),"") | H112: =IF(D112=1,'7811'!N8&"","") | I112: =IF(D112=1,'7811'!C8&"","") | J112: =IF(D112=1,'7811'!E8&"","") | K112: =IF(D112=1,'7811'!D8&"","") | L112: =IF(D112=1,IF('7811'!F8="","",'7811'!F8),"")
A113: 7811 – Teaching & Learning | B113: 7811 | C113: 9 | D113: =IF(AND(UPPER(TRIM('7811'!A9))="CHOICE",LEN(TRIM('7811'!E9&'7811'!F9))>0),1,0) | E113: =IF(D113=1,MAX(E$1:E112)+1,"") | F113: =IF(D113=1,IFERROR(CHOOSE(MATCH("X",'7811'!G9:L9,0),"①","②","③","④","⑤","⑥"),""),"") | G113: =IF(D113=1,IF('7811'!B9="","",'7811'!B9),"") | H113: =IF(D113=1,'7811'!N9&"","") | I113: =IF(D113=1,'7811'!C9&"","") | J113: =IF(D113=1,'7811'!E9&"","") | K113: =IF(D113=1,'7811'!D9&"","") | L113: =IF(D113=1,IF('7811'!F9="","",'7811'!F9),"")
A114: 7811 – Teaching & Learning | B114: 7811 | C114: 10 | D114: =IF(AND(UPPER(TRIM('7811'!A10))="CHOICE",LEN(TRIM('7811'!E10&'7811'!F10))>0),1,0) | E114: =IF(D114=1,MAX(E$1:E113)+1,"") | F114: =IF(D114=1,IFERROR(CHOOSE(MATCH("X",'7811'!G10:L10,0),"①","②","③","④","⑤","⑥"),""),"") | G114: =IF(D114=1,IF('7811'!B10="","",'7811'!B10),"") | H114: =IF(D114=1,'7811'!N10&"","") | I114: =IF(D114=1,'7811'!C10&"","") | J114: =IF(D114=1,'7811'!E10&"","") | K114: =IF(D114=1,'7811'!D10&"","") | L114: =IF(D114=1,IF('7811'!F10="","",'7811'!F10),"")
A115: 7811 – Teaching & Learning | B115: 7811 | C115: 11 | D115: =IF(AND(UPPER(TRIM('7811'!A11))="CHOICE",LEN(TRIM('7811'!E11&'7811'!F11))>0),1,0) | E115: =IF(D115=1,MAX(E$1:E114)+1,"") | F115: =IF(D115=1,IFERROR(CHOOSE(MATCH("X",'7811'!G11:L11,0),"①","②","③","④","⑤","⑥"),""),"") | G115: =IF(D115=1,IF('7811'!B11="","",'7811'!B11),"") | H115: =IF(D115=1,'7811'!N11&"","") | I115: =IF(D115=1,'7811'!C11&"","") | J115: =IF(D115=1,'7811'!E11&"","") | K115: =IF(D115=1,'7811'!D11&"","") | L115: =IF(D115=1,IF('7811'!F11="","",'7811'!F11),"")
A116: 7811 – Teaching & Learning | B116: 7811 | C116: 12 | D116: =IF(AND(UPPER(TRIM('7811'!A12))="CHOICE",LEN(TRIM('7811'!E12&'7811'!F12))>0),1,0) | E116: =IF(D116=1,MAX(E$1:E115)+1,"") | F116: =IF(D116=1,IFERROR(CHOOSE(MATCH("X",'7811'!G12:L12,0),"①","②","③","④","⑤","⑥"),""),"") | G116: =IF(D116=1,IF('7811'!B12="","",'7811'!B12),"") | H116: =IF(D116=1,'7811'!N12&"","") | I116: =IF(D116=1,'7811'!C12&"","") | J116: =IF(D116=1,'7811'!E12&"","") | K116: =IF(D116=1,'7811'!D12&"","") | L116: =IF(D116=1,IF('7811'!F12="","",'7811'!F12),"")
A117: 7811 – Teaching & Learning | B117: 7811 | C117: 13 | D117: =IF(AND(UPPER(TRIM('7811'!A13))="CHOICE",LEN(TRIM('7811'!E13&'7811'!F13))>0),1,0) | E117: =IF(D117=1,MAX(E$1:E116)+1,"") | F117: =IF(D117=1,IFERROR(CHOOSE(MATCH("X",'7811'!G13:L13,0),"①","②","③","④","⑤","⑥"),""),"") | G117: =IF(D117=1,IF('7811'!B13="","",'7811'!B13),"") | H117: =IF(D117=1,'7811'!N13&"","") | I117: =IF(D117=1,'7811'!C13&"","") | J117: =IF(D117=1,'7811'!E13&"","") | K117: =IF(D117=1,'7811'!D13&"","") | L117: =IF(D117=1,IF('7811'!F13="","",'7811'!F13),"")
A118: 7811 – Teaching & Learning | B118: 7811 | C118: 14 | D118: =IF(AND(UPPER(TRIM('7811'!A14))="CHOICE",LEN(TRIM('7811'!E14&'7811'!F14))>0),1,0) | E118: =IF(D118=1,MAX(E$1:E117)+1,"") | F118: =IF(D118=1,IFERROR(CHOOSE(MATCH("X",'7811'!G14:L14,0),"①","②","③","④","⑤","⑥"),""),"") | G118: =IF(D118=1,IF('7811'!B14="","",'7811'!B14),"") | H118: =IF(D118=1,'7811'!N14&"","") | I118: =IF(D118=1,'7811'!C14&"","") | J118: =IF(D118=1,'7811'!E14&"","") | K118: =IF(D118=1,'7811'!D14&"","") | L118: =IF(D118=1,IF('7811'!F14="","",'7811'!F14),"")
A119: 7811 – Teaching & Learning | B119: 7811 | C119: 15 | D119: =IF(AND(UPPER(TRIM('7811'!A15))="CHOICE",LEN(TRIM('7811'!E15&'7811'!F15))>0),1,0) | E119: =IF(D119=1,MAX(E$1:E118)+1,"") | F119: =IF(D119=1,IFERROR(CHOOSE(MATCH("X",'7811'!G15:L15,0),"①","②","③","④","⑤","⑥"),""),"") | G119: =IF(D119=1,IF('7811'!B15="","",'7811'!B15),"") | H119: =IF(D119=1,'7811'!N15&"","") | I119: =IF(D119=1,'7811'!C15&"","") | J119: =IF(D119=1,'7811'!E15&"","") | K119: =IF(D119=1,'7811'!D15&"","") | L119: =IF(D119=1,IF('7811'!F15="","",'7811'!F15),"")
A120: 7811 – Teaching & Learning | B120: 7811 | C120: 16 | D120: =IF(AND(UPPER(TRIM('7811'!A16))="CHOICE",LEN(TRIM('7811'!E16&'7811'!F16))>0),1,0) | E120: =IF(D120=1,MAX(E$1:E119)+1,"") | F120: =IF(D120=1,IFERROR(CHOOSE(MATCH("X",'7811'!G16:L16,0),"①","②","③","④","⑤","⑥"),""),"") | G120: =IF(D120=1,IF('7811'!B16="","",'7811'!B16),"") | H120: =IF(D120=1,'7811'!N16&"","") | I120: =IF(D120=1,'7811'!C16&"","") | J120: =IF(D120=1,'7811'!E16&"","") | K120: =IF(D120=1,'7811'!D16&"","") | L120: =IF(D120=1,IF('7811'!F16="","",'7811'!F16),"")
A121: 7811 – Teaching & Learning | B121: 7811 | C121: 17 | D121: =IF(AND(UPPER(TRIM('7811'!A17))="CHOICE",LEN(TRIM('7811'!E17&'7811'!F17))>0),1,0) | E121: =IF(D121=1,MAX(E$1:E120)+1,"") | F121: =IF(D121=1,IFERROR(CHOOSE(MATCH("X",'7811'!G17:L17,0),"①","②","③","④","⑤","⑥"),""),"") | G121: =IF(D121=1,IF('7811'!B17="","",'7811'!B17),"") | H121: =IF(D121=1,'7811'!N17&"","") | I121: =IF(D121=1,'7811'!C17&"","") | J121: =IF(D121=1,'7811'!E17&"","") | K121: =IF(D121=1,'7811'!D17&"","") | L121: =IF(D121=1,IF('7811'!F17="","",'7811'!F17),"")
... A163: 7811 – Teaching & Learning | B163: 7811 | C163: 59 | D163: =IF(AND(UPPER(TRIM('7811'!A59))="CHOICE",LEN(TRIM('7811'!E59&'7811'!F59))>0),1,0) | E163: =IF(D163=1,MAX(E$1:E162)+1,"") | F163: =IF(D163=1,IFERROR(CHOOSE(MATCH("X",'7811'!G59:L59,0),"①","②","③","④","⑤","⑥"),""),"") | G163: =IF(D163=1,IF('7811'!B59="","",'7811'!B59),"") | H163: =IF(D163=1,'7811'!N59&"","") | I163: =IF(D163=1,'7811'!C59&"","") | J163: =IF(D163=1,'7811'!E59&"","") | K163: =IF(D163=1,'7811'!D59&"","") | L163: =IF(D163=1,IF('7811'!F59="","",'7811'!F59),"")
A164: 7807 – Leadership I | B164: 7807 | C164: 6 | D164: =IF(AND(UPPER(TRIM('7807'!A6))="CHOICE",LEN(TRIM('7807'!E6&'7807'!F6))>0),1,0) | E164: =IF(D164=1,MAX(E$1:E163)+1,"") | F164: =IF(D164=1,IFERROR(CHOOSE(MATCH("X",'7807'!G6:L6,0),"①","②","③","④","⑤","⑥"),""),"") | G164: =IF(D164=1,IF('7807'!B6="","",'7807'!B6),"") | H164: =IF(D164=1,'7807'!N6&"","") | I164: =IF(D164=1,'7807'!C6&"","") | J164: =IF(D164=1,'7807'!E6&"","") | K164: =IF(D164=1,'7807'!D6&"","") | L164: =IF(D164=1,IF('7807'!F6="","",'7807'!F6),"")
A165: 7807 – Leadership I | B165: 7807 | C165: 7 | D165: =IF(AND(UPPER(TRIM('7807'!A7))="CHOICE",LEN(TRIM('7807'!E7&'7807'!F7))>0),1,0) | E165: =IF(D165=1,MAX(E$1:E164)+1,"") | F165: =IF(D165=1,IFERROR(CHOOSE(MATCH("X",'7807'!G7:L7,0),"①","②","③","④","⑤","⑥"),""),"") | G165: =IF(D165=1,IF('7807'!B7="","",'7807'!B7),"") | H165: =IF(D165=1,'7807'!N7&"","") | I165: =IF(D165=1,'7807'!C7&"","") | J165: =IF(D165=1,'7807'!E7&"","") | K165: =IF(D165=1,'7807'!D7&"","") | L165: =IF(D165=1,IF('7807'!F7="","",'7807'!F7),"")
A166: 7807 – Leadership I | B166: 7807 | C166: 8 | D166: =IF(AND(UPPER(TRIM('7807'!A8))="CHOICE",LEN(TRIM('7807'!E8&'7807'!F8))>0),1,0) | E166: =IF(D166=1,MAX(E$1:E165)+1,"") | F166: =IF(D166=1,IFERROR(CHOOSE(MATCH("X",'7807'!G8:L8,0),"①","②","③","④","⑤","⑥"),""),"") | G166: =IF(D166=1,IF('7807'!B8="","",'7807'!B8),"") | H166: =IF(D166=1,'7807'!N8&"","") | I166: =IF(D166=1,'7807'!C8&"","") | J166: =IF(D166=1,'7807'!E8&"","") | K166: =IF(D166=1,'7807'!D8&"","") | L166: =IF(D166=1,IF('7807'!F8="","",'7807'!F8),"")
A167: 7807 – Leadership I | B167: 7807 | C167: 9 | D167: =IF(AND(UPPER(TRIM('7807'!A9))="CHOICE",LEN(TRIM('7807'!E9&'7807'!F9))>0),1,0) | E167: =IF(D167=1,MAX(E$1:E166)+1,"") | F167: =IF(D167=1,IFERROR(CHOOSE(MATCH("X",'7807'!G9:L9,0),"①","②","③","④","⑤","⑥"),""),"") | G167: =IF(D167=1,IF('7807'!B9="","",'7807'!B9),"") | H167: =IF(D167=1,'7807'!N9&"","") | I167: =IF(D167=1,'7807'!C9&"","") | J167: =IF(D167=1,'7807'!E9&"","") | K167: =IF(D167=1,'7807'!D9&"","") | L167: =IF(D167=1,IF('7807'!F9="","",'7807'!F9),"")
A168: 7807 – Leadership I | B168: 7807 | C168: 10 | D168: =IF(AND(UPPER(TRIM('7807'!A10))="CHOICE",LEN(TRIM('7807'!E10&'7807'!F10))>0),1,0) | E168: =IF(D168=1,MAX(E$1:E167)+1,"") | F168: =IF(D168=1,IFERROR(CHOOSE(MATCH("X",'7807'!G10:L10,0),"①","②","③","④","⑤","⑥"),""),"") | G168: =IF(D168=1,IF('7807'!B10="","",'7807'!B10),"") | H168: =IF(D168=1,'7807'!N10&"","") | I168: =IF(D168=1,'7807'!C10&"","") | J168: =IF(D168=1,'7807'!E10&"","") | K168: =IF(D168=1,'7807'!D10&"","") | L168: =IF(D168=1,IF('7807'!F10="","",'7807'!F10),"")
A169: 7807 – Leadership I | B169: 7807 | C169: 11 | D169: =IF(AND(UPPER(TRIM('7807'!A11))="CHOICE",LEN(TRIM('7807'!E11&'7807'!F11))>0),1,0) | E169: =IF(D169=1,MAX(E$1:E168)+1,"") | F169: =IF(D169=1,IFERROR(CHOOSE(MATCH("X",'7807'!G11:L11,0),"①","②","③","④","⑤","⑥"),""),"") | G169: =IF(D169=1,IF('7807'!B11="","",'7807'!B11),"") | H169: =IF(D169=1,'7807'!N11&"","") | I169: =IF(D169=1,'7807'!C11&"","") | J169: =IF(D169=1,'7807'!E11&"","") | K169: =IF(D169=1,'7807'!D11&"","") | L169: =IF(D169=1,IF('7807'!F11="","",'7807'!F11),"")
A170: 7807 – Leadership I | B170: 7807 | C170: 12 | D170: =IF(AND(UPPER(TRIM('7807'!A12))="CHOICE",LEN(TRIM('7807'!E12&'7807'!F12))>0),1,0) | E170: =IF(D170=1,MAX(E$1:E169)+1,"") | F170: =IF(D170=1,IFERROR(CHOOSE(MATCH("X",'7807'!G12:L12,0),"①","②","③","④","⑤","⑥"),""),"") | G170: =IF(D170=1,IF('7807'!B12="","",'7807'!B12),"") | H170: =IF(D170=1,'7807'!N12&"","") | I170: =IF(D170=1,'7807'!C12&"","") | J170: =IF(D170=1,'7807'!E12&"","") | K170: =IF(D170=1,'7807'!D12&"","") | L170: =IF(D170=1,IF('7807'!F12="","",'7807'!F12),"")
A171: 7807 – Leadership I | B171: 7807 | C171: 13 | D171: =IF(AND(UPPER(TRIM('7807'!A13))="CHOICE",LEN(TRIM('7807'!E13&'7807'!F13))>0),1,0) | E171: =IF(D171=1,MAX(E$1:E170)+1,"") | F171: =IF(D171=1,IFERROR(CHOOSE(MATCH("X",'7807'!G13:L13,0),"①","②","③","④","⑤","⑥"),""),"") | G171: =IF(D171=1,IF('7807'!B13="","",'7807'!B13),"") | H171: =IF(D171=1,'7807'!N13&"","") | I171: =IF(D171=1,'7807'!C13&"","") | J171: =IF(D171=1,'7807'!E13&"","") | K171: =IF(D171=1,'7807'!D13&"","") | L171: =IF(D171=1,IF('7807'!F13="","",'7807'!F13),"")
A172: 7807 – Leadership I | B172: 7807 | C172: 14 | D172: =IF(AND(UPPER(TRIM('7807'!A14))="CHOICE",LEN(TRIM('7807'!E14&'7807'!F14))>0),1,0) | E172: =IF(D172=1,MAX(E$1:E171)+1,"") | F172: =IF(D172=1,IFERROR(CHOOSE(MATCH("X",'7807'!G14:L14,0),"①","②","③","④","⑤","⑥"),""),"") | G172: =IF(D172=1,IF('7807'!B14="","",'7807'!B14),"") | H172: =IF(D172=1,'7807'!N14&"","") | I172: =IF(D172=1,'7807'!C14&"","") | J172: =IF(D172=1,'7807'!E14&"","") | K172: =IF(D172=1,'7807'!D14&"","") | L172: =IF(D172=1,IF('7807'!F14="","",'7807'!F14),"")
A173: 7807 – Leadership I | B173: 7807 | C173: 15 | D173: =IF(AND(UPPER(TRIM('7807'!A15))="CHOICE",LEN(TRIM('7807'!E15&'7807'!F15))>0),1,0) | E173: =IF(D173=1,MAX(E$1:E172)+1,"") | F173: =IF(D173=1,IFERROR(CHOOSE(MATCH("X",'7807'!G15:L15,0),"①","②","③","④","⑤","⑥"),""),"") | G173: =IF(D173=1,IF('7807'!B15="","",'7807'!B15),"") | H173: =IF(D173=1,'7807'!N15&"","") | I173: =IF(D173=1,'7807'!C15&"","") | J173: =IF(D173=1,'7807'!E15&"","") | K173: =IF(D173=1,'7807'!D15&"","") | L173: =IF(D173=1,IF('7807'!F15="","",'7807'!F15),"")
A174: 7807 – Leadership I | B174: 7807 | C174: 16 | D174: =IF(AND(UPPER(TRIM('7807'!A16))="CHOICE",LEN(TRIM('7807'!E16&'7807'!F16))>0),1,0) | E174: =IF(D174=1,MAX(E$1:E173)+1,"") | F174: =IF(D174=1,IFERROR(CHOOSE(MATCH("X",'7807'!G16:L16,0),"①","②","③","④","⑤","⑥"),""),"") | G174: =IF(D174=1,IF('7807'!B16="","",'7807'!B16),"") | H174: =IF(D174=1,'7807'!N16&"","") | I174: =IF(D174=1,'7807'!C16&"","") | J174: =IF(D174=1,'7807'!E16&"","") | K174: =IF(D174=1,'7807'!D16&"","") | L174: =IF(D174=1,IF('7807'!F16="","",'7807'!F16),"")
A175: 7807 – Leadership I | B175: 7807 | C175: 17 | D175: =IF(AND(UPPER(TRIM('7807'!A17))="CHOICE",LEN(TRIM('7807'!E17&'7807'!F17))>0),1,0) | E175: =IF(D175=1,MAX(E$1:E174)+1,"") | F175: =IF(D175=1,IFERROR(CHOOSE(MATCH("X",'7807'!G17:L17,0),"①","②","③","④","⑤","⑥"),""),"") | G175: =IF(D175=1,IF('7807'!B17="","",'7807'!B17),"") | H175: =IF(D175=1,'7807'!N17&"","") | I175: =IF(D175=1,'7807'!C17&"","") | J175: =IF(D175=1,'7807'!E17&"","") | K175: =IF(D175=1,'7807'!D17&"","") | L175: =IF(D175=1,IF('7807'!F17="","",'7807'!F17),"")
... A217: 7807 – Leadership I | B217: 7807 | C217: 59 | D217: =IF(AND(UPPER(TRIM('7807'!A59))="CHOICE",LEN(TRIM('7807'!E59&'7807'!F59))>0),1,0) | E217: =IF(D217=1,MAX(E$1:E216)+1,"") | F217: =IF(D217=1,IFERROR(CHOOSE(MATCH("X",'7807'!G59:L59,0),"①","②","③","④","⑤","⑥"),""),"") | G217: =IF(D217=1,IF('7807'!B59="","",'7807'!B59),"") | H217: =IF(D217=1,'7807'!N59&"","") | I217: =IF(D217=1,'7807'!C59&"","") | J217: =IF(D217=1,'7807'!E59&"","") | K217: =IF(D217=1,'7807'!D59&"","") | L217: =IF(D217=1,IF('7807'!F59="","",'7807'!F59),"")
A218: 7810 – School Law & Policy | B218: 7810 | C218: 6 | D218: =IF(AND(UPPER(TRIM('7810'!A6))="CHOICE",LEN(TRIM('7810'!E6&'7810'!F6))>0),1,0) | E218: =IF(D218=1,MAX(E$1:E217)+1,"") | F218: =IF(D218=1,IFERROR(CHOOSE(MATCH("X",'7810'!G6:L6,0),"①","②","③","④","⑤","⑥"),""),"") | G218: =IF(D218=1,IF('7810'!B6="","",'7810'!B6),"") | H218: =IF(D218=1,'7810'!N6&"","") | I218: =IF(D218=1,'7810'!C6&"","") | J218: =IF(D218=1,'7810'!E6&"","") | K218: =IF(D218=1,'7810'!D6&"","") | L218: =IF(D218=1,IF('7810'!F6="","",'7810'!F6),"")
A219: 7810 – School Law & Policy | B219: 7810 | C219: 7 | D219: =IF(AND(UPPER(TRIM('7810'!A7))="CHOICE",LEN(TRIM('7810'!E7&'7810'!F7))>0),1,0) | E219: =IF(D219=1,MAX(E$1:E218)+1,"") | F219: =IF(D219=1,IFERROR(CHOOSE(MATCH("X",'7810'!G7:L7,0),"①","②","③","④","⑤","⑥"),""),"") | G219: =IF(D219=1,IF('7810'!B7="","",'7810'!B7),"") | H219: =IF(D219=1,'7810'!N7&"","") | I219: =IF(D219=1,'7810'!C7&"","") | J219: =IF(D219=1,'7810'!E7&"","") | K219: =IF(D219=1,'7810'!D7&"","") | L219: =IF(D219=1,IF('7810'!F7="","",'7810'!F7),"")
A220: 7810 – School Law & Policy | B220: 7810 | C220: 8 | D220: =IF(AND(UPPER(TRIM('7810'!A8))="CHOICE",LEN(TRIM('7810'!E8&'7810'!F8))>0),1,0) | E220: =IF(D220=1,MAX(E$1:E219)+1,"") | F220: =IF(D220=1,IFERROR(CHOOSE(MATCH("X",'7810'!G8:L8,0),"①","②","③","④","⑤","⑥"),""),"") | G220: =IF(D220=1,IF('7810'!B8="","",'7810'!B8),"") | H220: =IF(D220=1,'7810'!N8&"","") | I220: =IF(D220=1,'7810'!C8&"","") | J220: =IF(D220=1,'7810'!E8&"","") | K220: =IF(D220=1,'7810'!D8&"","") | L220: =IF(D220=1,IF('7810'!F8="","",'7810'!F8),"")
A221: 7810 – School Law & Policy | B221: 7810 | C221: 9 | D221: =IF(AND(UPPER(TRIM('7810'!A9))="CHOICE",LEN(TRIM('7810'!E9&'7810'!F9))>0),1,0) | E221: =IF(D221=1,MAX(E$1:E220)+1,"") | F221: =IF(D221=1,IFERROR(CHOOSE(MATCH("X",'7810'!G9:L9,0),"①","②","③","④","⑤","⑥"),""),"") | G221: =IF(D221=1,IF('7810'!B9="","",'7810'!B9),"") | H221: =IF(D221=1,'7810'!N9&"","") | I221: =IF(D221=1,'7810'!C9&"","") | J221: =IF(D221=1,'7810'!E9&"","") | K221: =IF(D221=1,'7810'!D9&"","") | L221: =IF(D221=1,IF('7810'!F9="","",'7810'!F9),"")
A222: 7810 – School Law & Policy | B222: 7810 | C222: 10 | D222: =IF(AND(UPPER(TRIM('7810'!A10))="CHOICE",LEN(TRIM('7810'!E10&'7810'!F10))>0),1,0) | E222: =IF(D222=1,MAX(E$1:E221)+1,"") | F222: =IF(D222=1,IFERROR(CHOOSE(MATCH("X",'7810'!G10:L10,0),"①","②","③","④","⑤","⑥"),""),"") | G222: =IF(D222=1,IF('7810'!B10="","",'7810'!B10),"") | H222: =IF(D222=1,'7810'!N10&"","") | I222: =IF(D222=1,'7810'!C10&"","") | J222: =IF(D222=1,'7810'!E10&"","") | K222: =IF(D222=1,'7810'!D10&"","") | L222: =IF(D222=1,IF('7810'!F10="","",'7810'!F10),"")
A223: 7810 – School Law & Policy | B223: 7810 | C223: 11 | D223: =IF(AND(UPPER(TRIM('7810'!A11))="CHOICE",LEN(TRIM('7810'!E11&'7810'!F11))>0),1,0) | E223: =IF(D223=1,MAX(E$1:E222)+1,"") | F223: =IF(D223=1,IFERROR(CHOOSE(MATCH("X",'7810'!G11:L11,0),"①","②","③","④","⑤","⑥"),""),"") | G223: =IF(D223=1,IF('7810'!B11="","",'7810'!B11),"") | H223: =IF(D223=1,'7810'!N11&"","") | I223: =IF(D223=1,'7810'!C11&"","") | J223: =IF(D223=1,'7810'!E11&"","") | K223: =IF(D223=1,'7810'!D11&"","") | L223: =IF(D223=1,IF('7810'!F11="","",'7810'!F11),"")
A224: 7810 – School Law & Policy | B224: 7810 | C224: 12 | D224: =IF(AND(UPPER(TRIM('7810'!A12))="CHOICE",LEN(TRIM('7810'!E12&'7810'!F12))>0),1,0) | E224: =IF(D224=1,MAX(E$1:E223)+1,"") | F224: =IF(D224=1,IFERROR(CHOOSE(MATCH("X",'7810'!G12:L12,0),"①","②","③","④","⑤","⑥"),""),"") | G224: =IF(D224=1,IF('7810'!B12="","",'7810'!B12),"") | H224: =IF(D224=1,'7810'!N12&"","") | I224: =IF(D224=1,'7810'!C12&"","") | J224: =IF(D224=1,'7810'!E12&"","") | K224: =IF(D224=1,'7810'!D12&"","") | L224: =IF(D224=1,IF('7810'!F12="","",'7810'!F12),"")
A225: 7810 – School Law & Policy | B225: 7810 | C225: 13 | D225: =IF(AND(UPPER(TRIM('7810'!A13))="CHOICE",LEN(TRIM('7810'!E13&'7810'!F13))>0),1,0) | E225: =IF(D225=1,MAX(E$1:E224)+1,"") | F225: =IF(D225=1,IFERROR(CHOOSE(MATCH("X",'7810'!G13:L13,0),"①","②","③","④","⑤","⑥"),""),"") | G225: =IF(D225=1,IF('7810'!B13="","",'7810'!B13),"") | H225: =IF(D225=1,'7810'!N13&"","") | I225: =IF(D225=1,'7810'!C13&"","") | J225: =IF(D225=1,'7810'!E13&"","") | K225: =IF(D225=1,'7810'!D13&"","") | L225: =IF(D225=1,IF('7810'!F13="","",'7810'!F13),"")
A226: 7810 – School Law & Policy | B226: 7810 | C226: 14 | D226: =IF(AND(UPPER(TRIM('7810'!A14))="CHOICE",LEN(TRIM('7810'!E14&'7810'!F14))>0),1,0) | E226: =IF(D226=1,MAX(E$1:E225)+1,"") | F226: =IF(D226=1,IFERROR(CHOOSE(MATCH("X",'7810'!G14:L14,0),"①","②","③","④","⑤","⑥"),""),"") | G226: =IF(D226=1,IF('7810'!B14="","",'7810'!B14),"") | H226: =IF(D226=1,'7810'!N14&"","") | I226: =IF(D226=1,'7810'!C14&"","") | J226: =IF(D226=1,'7810'!E14&"","") | K226: =IF(D226=1,'7810'!D14&"","") | L226: =IF(D226=1,IF('7810'!F14="","",'7810'!F14),"")
A227: 7810 – School Law & Policy | B227: 7810 | C227: 15 | D227: =IF(AND(UPPER(TRIM('7810'!A15))="CHOICE",LEN(TRIM('7810'!E15&'7810'!F15))>0),1,0) | E227: =IF(D227=1,MAX(E$1:E226)+1,"") | F227: =IF(D227=1,IFERROR(CHOOSE(MATCH("X",'7810'!G15:L15,0),"①","②","③","④","⑤","⑥"),""),"") | G227: =IF(D227=1,IF('7810'!B15="","",'7810'!B15),"") | H227: =IF(D227=1,'7810'!N15&"","") | I227: =IF(D227=1,'7810'!C15&"","") | J227: =IF(D227=1,'7810'!E15&"","") | K227: =IF(D227=1,'7810'!D15&"","") | L227: =IF(D227=1,IF('7810'!F15="","",'7810'!F15),"")
A228: 7810 – School Law & Policy | B228: 7810 | C228: 16 | D228: =IF(AND(UPPER(TRIM('7810'!A16))="CHOICE",LEN(TRIM('7810'!E16&'7810'!F16))>0),1,0) | E228: =IF(D228=1,MAX(E$1:E227)+1,"") | F228: =IF(D228=1,IFERROR(CHOOSE(MATCH("X",'7810'!G16:L16,0),"①","②","③","④","⑤","⑥"),""),"") | G228: =IF(D228=1,IF('7810'!B16="","",'7810'!B16),"") | H228: =IF(D228=1,'7810'!N16&"","") | I228: =IF(D228=1,'7810'!C16&"","") | J228: =IF(D228=1,'7810'!E16&"","") | K228: =IF(D228=1,'7810'!D16&"","") | L228: =IF(D228=1,IF('7810'!F16="","",'7810'!F16),"")
A229: 7810 – School Law & Policy | B229: 7810 | C229: 17 | D229: =IF(AND(UPPER(TRIM('7810'!A17))="CHOICE",LEN(TRIM('7810'!E17&'7810'!F17))>0),1,0) | E229: =IF(D229=1,MAX(E$1:E228)+1,"") | F229: =IF(D229=1,IFERROR(CHOOSE(MATCH("X",'7810'!G17:L17,0),"①","②","③","④","⑤","⑥"),""),"") | G229: =IF(D229=1,IF('7810'!B17="","",'7810'!B17),"") | H229: =IF(D229=1,'7810'!N17&"","") | I229: =IF(D229=1,'7810'!C17&"","") | J229: =IF(D229=1,'7810'!E17&"","") | K229: =IF(D229=1,'7810'!D17&"","") | L229: =IF(D229=1,IF('7810'!F17="","",'7810'!F17),"")
... A271: 7810 – School Law & Policy | B271: 7810 | C271: 59 | D271: =IF(AND(UPPER(TRIM('7810'!A59))="CHOICE",LEN(TRIM('7810'!E59&'7810'!F59))>0),1,0) | E271: =IF(D271=1,MAX(E$1:E270)+1,"") | F271: =IF(D271=1,IFERROR(CHOOSE(MATCH("X",'7810'!G59:L59,0),"①","②","③","④","⑤","⑥"),""),"") | G271: =IF(D271=1,IF('7810'!B59="","",'7810'!B59),"") | H271: =IF(D271=1,'7810'!N59&"","") | I271: =IF(D271=1,'7810'!C59&"","") | J271: =IF(D271=1,'7810'!E59&"","") | K271: =IF(D271=1,'7810'!D59&"","") | L271: =IF(D271=1,IF('7810'!F59="","",'7810'!F59),"")
A272: 7140 – Leadership II (LEAD II) | B272: 7140 | C272: 6 | D272: =IF(AND(UPPER(TRIM('7140'!A6))="CHOICE",LEN(TRIM('7140'!E6&'7140'!F6))>0),1,0) | E272: =IF(D272=1,MAX(E$1:E271)+1,"") | F272: =IF(D272=1,IFERROR(CHOOSE(MATCH("X",'7140'!G6:L6,0),"①","②","③","④","⑤","⑥"),""),"") | G272: =IF(D272=1,IF('7140'!B6="","",'7140'!B6),"") | H272: =IF(D272=1,'7140'!N6&"","") | I272: =IF(D272=1,'7140'!C6&"","") | J272: =IF(D272=1,'7140'!E6&"","") | K272: =IF(D272=1,'7140'!D6&"","") | L272: =IF(D272=1,IF('7140'!F6="","",'7140'!F6),"")
A273: 7140 – Leadership II (LEAD II) | B273: 7140 | C273: 7 | D273: =IF(AND(UPPER(TRIM('7140'!A7))="CHOICE",LEN(TRIM('7140'!E7&'7140'!F7))>0),1,0) | E273: =IF(D273=1,MAX(E$1:E272)+1,"") | F273: =IF(D273=1,IFERROR(CHOOSE(MATCH("X",'7140'!G7:L7,0),"①","②","③","④","⑤","⑥"),""),"") | G273: =IF(D273=1,IF('7140'!B7="","",'7140'!B7),"") | H273: =IF(D273=1,'7140'!N7&"","") | I273: =IF(D273=1,'7140'!C7&"","") | J273: =IF(D273=1,'7140'!E7&"","") | K273: =IF(D273=1,'7140'!D7&"","") | L273: =IF(D273=1,IF('7140'!F7="","",'7140'!F7),"")
A274: 7140 – Leadership II (LEAD II) | B274: 7140 | C274: 8 | D274: =IF(AND(UPPER(TRIM('7140'!A8))="CHOICE",LEN(TRIM('7140'!E8&'7140'!F8))>0),1,0) | E274: =IF(D274=1,MAX(E$1:E273)+1,"") | F274: =IF(D274=1,IFERROR(CHOOSE(MATCH("X",'7140'!G8:L8,0),"①","②","③","④","⑤","⑥"),""),"") | G274: =IF(D274=1,IF('7140'!B8="","",'7140'!B8),"") | H274: =IF(D274=1,'7140'!N8&"","") | I274: =IF(D274=1,'7140'!C8&"","") | J274: =IF(D274=1,'7140'!E8&"","") | K274: =IF(D274=1,'7140'!D8&"","") | L274: =IF(D274=1,IF('7140'!F8="","",'7140'!F8),"")
A275: 7140 – Leadership II (LEAD II) | B275: 7140 | C275: 9 | D275: =IF(AND(UPPER(TRIM('7140'!A9))="CHOICE",LEN(TRIM('7140'!E9&'7140'!F9))>0),1,0) | E275: =IF(D275=1,MAX(E$1:E274)+1,"") | F275: =IF(D275=1,IFERROR(CHOOSE(MATCH("X",'7140'!G9:L9,0),"①","②","③","④","⑤","⑥"),""),"") | G275: =IF(D275=1,IF('7140'!B9="","",'7140'!B9),"") | H275: =IF(D275=1,'7140'!N9&"","") | I275: =IF(D275=1,'7140'!C9&"","") | J275: =IF(D275=1,'7140'!E9&"","") | K275: =IF(D275=1,'7140'!D9&"","") | L275: =IF(D275=1,IF('7140'!F9="","",'7140'!F9),"")
A276: 7140 – Leadership II (LEAD II) | B276: 7140 | C276: 10 | D276: =IF(AND(UPPER(TRIM('7140'!A10))="CHOICE",LEN(TRIM('7140'!E10&'7140'!F10))>0),1,0) | E276: =IF(D276=1,MAX(E$1:E275)+1,"") | F276: =IF(D276=1,IFERROR(CHOOSE(MATCH("X",'7140'!G10:L10,0),"①","②","③","④","⑤","⑥"),""),"") | G276: =IF(D276=1,IF('7140'!B10="","",'7140'!B10),"") | H276: =IF(D276=1,'7140'!N10&"","") | I276: =IF(D276=1,'7140'!C10&"","") | J276: =IF(D276=1,'7140'!E10&"","") | K276: =IF(D276=1,'7140'!D10&"","") | L276: =IF(D276=1,IF('7140'!F10="","",'7140'!F10),"")
A277: 7140 – Leadership II (LEAD II) | B277: 7140 | C277: 11 | D277: =IF(AND(UPPER(TRIM('7140'!A11))="CHOICE",LEN(TRIM('7140'!E11&'7140'!F11))>0),1,0) | E277: =IF(D277=1,MAX(E$1:E276)+1,"") | F277: =IF(D277=1,IFERROR(CHOOSE(MATCH("X",'7140'!G11:L11,0),"①","②","③","④","⑤","⑥"),""),"") | G277: =IF(D277=1,IF('7140'!B11="","",'7140'!B11),"") | H277: =IF(D277=1,'7140'!N11&"","") | I277: =IF(D277=1,'7140'!C11&"","") | J277: =IF(D277=1,'7140'!E11&"","") | K277: =IF(D277=1,'7140'!D11&"","") | L277: =IF(D277=1,IF('7140'!F11="","",'7140'!F11),"")
A278: 7140 – Leadership II (LEAD II) | B278: 7140 | C278: 12 | D278: =IF(AND(UPPER(TRIM('7140'!A12))="CHOICE",LEN(TRIM('7140'!E12&'7140'!F12))>0),1,0) | E278: =IF(D278=1,MAX(E$1:E277)+1,"") | F278: =IF(D278=1,IFERROR(CHOOSE(MATCH("X",'7140'!G12:L12,0),"①","②","③","④","⑤","⑥"),""),"") | G278: =IF(D278=1,IF('7140'!B12="","",'7140'!B12),"") | H278: =IF(D278=1,'7140'!N12&"","") | I278: =IF(D278=1,'7140'!C12&"","") | J278: =IF(D278=1,'7140'!E12&"","") | K278: =IF(D278=1,'7140'!D12&"","") | L278: =IF(D278=1,IF('7140'!F12="","",'7140'!F12),"")
A279: 7140 – Leadership II (LEAD II) | B279: 7140 | C279: 13 | D279: =IF(AND(UPPER(TRIM('7140'!A13))="CHOICE",LEN(TRIM('7140'!E13&'7140'!F13))>0),1,0) | E279: =IF(D279=1,MAX(E$1:E278)+1,"") | F279: =IF(D279=1,IFERROR(CHOOSE(MATCH("X",'7140'!G13:L13,0),"①","②","③","④","⑤","⑥"),""),"") | G279: =IF(D279=1,IF('7140'!B13="","",'7140'!B13),"") | H279: =IF(D279=1,'7140'!N13&"","") | I279: =IF(D279=1,'7140'!C13&"","") | J279: =IF(D279=1,'7140'!E13&"","") | K279: =IF(D279=1,'7140'!D13&"","") | L279: =IF(D279=1,IF('7140'!F13="","",'7140'!F13),"")
A280: 7140 – Leadership II (LEAD II) | B280: 7140 | C280: 14 | D280: =IF(AND(UPPER(TRIM('7140'!A14))="CHOICE",LEN(TRIM('7140'!E14&'7140'!F14))>0),1,0) | E280: =IF(D280=1,MAX(E$1:E279)+1,"") | F280: =IF(D280=1,IFERROR(CHOOSE(MATCH("X",'7140'!G14:L14,0),"①","②","③","④","⑤","⑥"),""),"") | G280: =IF(D280=1,IF('7140'!B14="","",'7140'!B14),"") | H280: =IF(D280=1,'7140'!N14&"","") | I280: =IF(D280=1,'7140'!C14&"","") | J280: =IF(D280=1,'7140'!E14&"","") | K280: =IF(D280=1,'7140'!D14&"","") | L280: =IF(D280=1,IF('7140'!F14="","",'7140'!F14),"")
A281: 7140 – Leadership II (LEAD II) | B281: 7140 | C281: 15 | D281: =IF(AND(UPPER(TRIM('7140'!A15))="CHOICE",LEN(TRIM('7140'!E15&'7140'!F15))>0),1,0) | E281: =IF(D281=1,MAX(E$1:E280)+1,"") | F281: =IF(D281=1,IFERROR(CHOOSE(MATCH("X",'7140'!G15:L15,0),"①","②","③","④","⑤","⑥"),""),"") | G281: =IF(D281=1,IF('7140'!B15="","",'7140'!B15),"") | H281: =IF(D281=1,'7140'!N15&"","") | I281: =IF(D281=1,'7140'!C15&"","") | J281: =IF(D281=1,'7140'!E15&"","") | K281: =IF(D281=1,'7140'!D15&"","") | L281: =IF(D281=1,IF('7140'!F15="","",'7140'!F15),"")
A282: 7140 – Leadership II (LEAD II) | B282: 7140 | C282: 16 | D282: =IF(AND(UPPER(TRIM('7140'!A16))="CHOICE",LEN(TRIM('7140'!E16&'7140'!F16))>0),1,0) | E282: =IF(D282=1,MAX(E$1:E281)+1,"") | F282: =IF(D282=1,IFERROR(CHOOSE(MATCH("X",'7140'!G16:L16,0),"①","②","③","④","⑤","⑥"),""),"") | G282: =IF(D282=1,IF('7140'!B16="","",'7140'!B16),"") | H282: =IF(D282=1,'7140'!N16&"","") | I282: =IF(D282=1,'7140'!C16&"","") | J282: =IF(D282=1,'7140'!E16&"","") | K282: =IF(D282=1,'7140'!D16&"","") | L282: =IF(D282=1,IF('7140'!F16="","",'7140'!F16),"")
A283: 7140 – Leadership II (LEAD II) | B283: 7140 | C283: 17 | D283: =IF(AND(UPPER(TRIM('7140'!A17))="CHOICE",LEN(TRIM('7140'!E17&'7140'!F17))>0),1,0) | E283: =IF(D283=1,MAX(E$1:E282)+1,"") | F283: =IF(D283=1,IFERROR(CHOOSE(MATCH("X",'7140'!G17:L17,0),"①","②","③","④","⑤","⑥"),""),"") | G283: =IF(D283=1,IF('7140'!B17="","",'7140'!B17),"") | H283: =IF(D283=1,'7140'!N17&"","") | I283: =IF(D283=1,'7140'!C17&"","") | J283: =IF(D283=1,'7140'!E17&"","") | K283: =IF(D283=1,'7140'!D17&"","") | L283: =IF(D283=1,IF('7140'!F17="","",'7140'!F17),"")
... A325: 7140 – Leadership II (LEAD II) | B325: 7140 | C325: 59 | D325: =IF(AND(UPPER(TRIM('7140'!A59))="CHOICE",LEN(TRIM('7140'!E59&'7140'!F59))>0),1,0) | E325: =IF(D325=1,MAX(E$1:E324)+1,"") | F325: =IF(D325=1,IFERROR(CHOOSE(MATCH("X",'7140'!G59:L59,0),"①","②","③","④","⑤","⑥"),""),"") | G325: =IF(D325=1,IF('7140'!B59="","",'7140'!B59),"") | H325: =IF(D325=1,'7140'!N59&"","") | I325: =IF(D325=1,'7140'!C59&"","") | J325: =IF(D325=1,'7140'!E59&"","") | K325: =IF(D325=1,'7140'!D59&"","") | L325: =IF(D325=1,IF('7140'!F59="","",'7140'!F59),"")
A326: 7808 – School Finance | B326: 7808 | C326: 6 | D326: =IF(AND(UPPER(TRIM('7808'!A6))="CHOICE",LEN(TRIM('7808'!E6&'7808'!F6))>0),1,0) | E326: =IF(D326=1,MAX(E$1:E325)+1,"") | F326: =IF(D326=1,IFERROR(CHOOSE(MATCH("X",'7808'!G6:L6,0),"①","②","③","④","⑤","⑥"),""),"") | G326: =IF(D326=1,IF('7808'!B6="","",'7808'!B6),"") | H326: =IF(D326=1,'7808'!N6&"","") | I326: =IF(D326=1,'7808'!C6&"","") | J326: =IF(D326=1,'7808'!E6&"","") | K326: =IF(D326=1,'7808'!D6&"","") | L326: =IF(D326=1,IF('7808'!F6="","",'7808'!F6),"")
A327: 7808 – School Finance | B327: 7808 | C327: 7 | D327: =IF(AND(UPPER(TRIM('7808'!A7))="CHOICE",LEN(TRIM('7808'!E7&'7808'!F7))>0),1,0) | E327: =IF(D327=1,MAX(E$1:E326)+1,"") | F327: =IF(D327=1,IFERROR(CHOOSE(MATCH("X",'7808'!G7:L7,0),"①","②","③","④","⑤","⑥"),""),"") | G327: =IF(D327=1,IF('7808'!B7="","",'7808'!B7),"") | H327: =IF(D327=1,'7808'!N7&"","") | I327: =IF(D327=1,'7808'!C7&"","") | J327: =IF(D327=1,'7808'!E7&"","") | K327: =IF(D327=1,'7808'!D7&"","") | L327: =IF(D327=1,IF('7808'!F7="","",'7808'!F7),"")
A328: 7808 – School Finance | B328: 7808 | C328: 8 | D328: =IF(AND(UPPER(TRIM('7808'!A8))="CHOICE",LEN(TRIM('7808'!E8&'7808'!F8))>0),1,0) | E328: =IF(D328=1,MAX(E$1:E327)+1,"") | F328: =IF(D328=1,IFERROR(CHOOSE(MATCH("X",'7808'!G8:L8,0),"①","②","③","④","⑤","⑥"),""),"") | G328: =IF(D328=1,IF('7808'!B8="","",'7808'!B8),"") | H328: =IF(D328=1,'7808'!N8&"","") | I328: =IF(D328=1,'7808'!C8&"","") | J328: =IF(D328=1,'7808'!E8&"","") | K328: =IF(D328=1,'7808'!D8&"","") | L328: =IF(D328=1,IF('7808'!F8="","",'7808'!F8),"")
A329: 7808 – School Finance | B329: 7808 | C329: 9 | D329: =IF(AND(UPPER(TRIM('7808'!A9))="CHOICE",LEN(TRIM('7808'!E9&'7808'!F9))>0),1,0) | E329: =IF(D329=1,MAX(E$1:E328)+1,"") | F329: =IF(D329=1,IFERROR(CHOOSE(MATCH("X",'7808'!G9:L9,0),"①","②","③","④","⑤","⑥"),""),"") | G329: =IF(D329=1,IF('7808'!B9="","",'7808'!B9),"") | H329: =IF(D329=1,'7808'!N9&"","") | I329: =IF(D329=1,'7808'!C9&"","") | J329: =IF(D329=1,'7808'!E9&"","") | K329: =IF(D329=1,'7808'!D9&"","") | L329: =IF(D329=1,IF('7808'!F9="","",'7808'!F9),"")
A330: 7808 – School Finance | B330: 7808 | C330: 10 | D330: =IF(AND(UPPER(TRIM('7808'!A10))="CHOICE",LEN(TRIM('7808'!E10&'7808'!F10))>0),1,0) | E330: =IF(D330=1,MAX(E$1:E329)+1,"") | F330: =IF(D330=1,IFERROR(CHOOSE(MATCH("X",'7808'!G10:L10,0),"①","②","③","④","⑤","⑥"),""),"") | G330: =IF(D330=1,IF('7808'!B10="","",'7808'!B10),"") | H330: =IF(D330=1,'7808'!N10&"","") | I330: =IF(D330=1,'7808'!C10&"","") | J330: =IF(D330=1,'7808'!E10&"","") | K330: =IF(D330=1,'7808'!D10&"","") | L330: =IF(D330=1,IF('7808'!F10="","",'7808'!F10),"")
A331: 7808 – School Finance | B331: 7808 | C331: 11 | D331: =IF(AND(UPPER(TRIM('7808'!A11))="CHOICE",LEN(TRIM('7808'!E11&'7808'!F11))>0),1,0) | E331: =IF(D331=1,MAX(E$1:E330)+1,"") | F331: =IF(D331=1,IFERROR(CHOOSE(MATCH("X",'7808'!G11:L11,0),"①","②","③","④","⑤","⑥"),""),"") | G331: =IF(D331=1,IF('7808'!B11="","",'7808'!B11),"") | H331: =IF(D331=1,'7808'!N11&"","") | I331: =IF(D331=1,'7808'!C11&"","") | J331: =IF(D331=1,'7808'!E11&"","") | K331: =IF(D331=1,'7808'!D11&"","") | L331: =IF(D331=1,IF('7808'!F11="","",'7808'!F11),"")
A332: 7808 – School Finance | B332: 7808 | C332: 12 | D332: =IF(AND(UPPER(TRIM('7808'!A12))="CHOICE",LEN(TRIM('7808'!E12&'7808'!F12))>0),1,0) | E332: =IF(D332=1,MAX(E$1:E331)+1,"") | F332: =IF(D332=1,IFERROR(CHOOSE(MATCH("X",'7808'!G12:L12,0),"①","②","③","④","⑤","⑥"),""),"") | G332: =IF(D332=1,IF('7808'!B12="","",'7808'!B12),"") | H332: =IF(D332=1,'7808'!N12&"","") | I332: =IF(D332=1,'7808'!C12&"","") | J332: =IF(D332=1,'7808'!E12&"","") | K332: =IF(D332=1,'7808'!D12&"","") | L332: =IF(D332=1,IF('7808'!F12="","",'7808'!F12),"")
A333: 7808 – School Finance | B333: 7808 | C333: 13 | D333: =IF(AND(UPPER(TRIM('7808'!A13))="CHOICE",LEN(TRIM('7808'!E13&'7808'!F13))>0),1,0) | E333: =IF(D333=1,MAX(E$1:E332)+1,"") | F333: =IF(D333=1,IFERROR(CHOOSE(MATCH("X",'7808'!G13:L13,0),"①","②","③","④","⑤","⑥"),""),"") | G333: =IF(D333=1,IF('7808'!B13="","",'7808'!B13),"") | H333: =IF(D333=1,'7808'!N13&"","") | I333: =IF(D333=1,'7808'!C13&"","") | J333: =IF(D333=1,'7808'!E13&"","") | K333: =IF(D333=1,'7808'!D13&"","") | L333: =IF(D333=1,IF('7808'!F13="","",'7808'!F13),"")
A334: 7808 – School Finance | B334: 7808 | C334: 14 | D334: =IF(AND(UPPER(TRIM('7808'!A14))="CHOICE",LEN(TRIM('7808'!E14&'7808'!F14))>0),1,0) | E334: =IF(D334=1,MAX(E$1:E333)+1,"") | F334: =IF(D334=1,IFERROR(CHOOSE(MATCH("X",'7808'!G14:L14,0),"①","②","③","④","⑤","⑥"),""),"") | G334: =IF(D334=1,IF('7808'!B14="","",'7808'!B14),"") | H334: =IF(D334=1,'7808'!N14&"","") | I334: =IF(D334=1,'7808'!C14&"","") | J334: =IF(D334=1,'7808'!E14&"","") | K334: =IF(D334=1,'7808'!D14&"","") | L334: =IF(D334=1,IF('7808'!F14="","",'7808'!F14),"")
A335: 7808 – School Finance | B335: 7808 | C335: 15 | D335: =IF(AND(UPPER(TRIM('7808'!A15))="CHOICE",LEN(TRIM('7808'!E15&'7808'!F15))>0),1,0) | E335: =IF(D335=1,MAX(E$1:E334)+1,"") | F335: =IF(D335=1,IFERROR(CHOOSE(MATCH("X",'7808'!G15:L15,0),"①","②","③","④","⑤","⑥"),""),"") | G335: =IF(D335=1,IF('7808'!B15="","",'7808'!B15),"") | H335: =IF(D335=1,'7808'!N15&"","") | I335: =IF(D335=1,'7808'!C15&"","") | J335: =IF(D335=1,'7808'!E15&"","") | K335: =IF(D335=1,'7808'!D15&"","") | L335: =IF(D335=1,IF('7808'!F15="","",'7808'!F15),"")
A336: 7808 – School Finance | B336: 7808 | C336: 16 | D336: =IF(AND(UPPER(TRIM('7808'!A16))="CHOICE",LEN(TRIM('7808'!E16&'7808'!F16))>0),1,0) | E336: =IF(D336=1,MAX(E$1:E335)+1,"") | F336: =IF(D336=1,IFERROR(CHOOSE(MATCH("X",'7808'!G16:L16,0),"①","②","③","④","⑤","⑥"),""),"") | G336: =IF(D336=1,IF('7808'!B16="","",'7808'!B16),"") | H336: =IF(D336=1,'7808'!N16&"","") | I336: =IF(D336=1,'7808'!C16&"","") | J336: =IF(D336=1,'7808'!E16&"","") | K336: =IF(D336=1,'7808'!D16&"","") | L336: =IF(D336=1,IF('7808'!F16="","",'7808'!F16),"")
A337: 7808 – School Finance | B337: 7808 | C337: 17 | D337: =IF(AND(UPPER(TRIM('7808'!A17))="CHOICE",LEN(TRIM('7808'!E17&'7808'!F17))>0),1,0) | E337: =IF(D337=1,MAX(E$1:E336)+1,"") | F337: =IF(D337=1,IFERROR(CHOOSE(MATCH("X",'7808'!G17:L17,0),"①","②","③","④","⑤","⑥"),""),"") | G337: =IF(D337=1,IF('7808'!B17="","",'7808'!B17),"") | H337: =IF(D337=1,'7808'!N17&"","") | I337: =IF(D337=1,'7808'!C17&"","") | J337: =IF(D337=1,'7808'!E17&"","") | K337: =IF(D337=1,'7808'!D17&"","") | L337: =IF(D337=1,IF('7808'!F17="","",'7808'!F17),"")
... A379: 7808 – School Finance | B379: 7808 | C379: 59 | D379: =IF(AND(UPPER(TRIM('7808'!A59))="CHOICE",LEN(TRIM('7808'!E59&'7808'!F59))>0),1,0) | E379: =IF(D379=1,MAX(E$1:E378)+1,"") | F379: =IF(D379=1,IFERROR(CHOOSE(MATCH("X",'7808'!G59:L59,0),"①","②","③","④","⑤","⑥"),""),"") | G379: =IF(D379=1,IF('7808'!B59="","",'7808'!B59),"") | H379: =IF(D379=1,'7808'!N59&"","") | I379: =IF(D379=1,'7808'!C59&"","") | J379: =IF(D379=1,'7808'!E59&"","") | K379: =IF(D379=1,'7808'!D59&"","") | L379: =IF(D379=1,IF('7808'!F59="","",'7808'!F59),"")
A380: 7805 – Cultivating Professional Capacity | B380: 7805 | C380: 6 | D380: =IF(AND(UPPER(TRIM('7805'!A6))="CHOICE",LEN(TRIM('7805'!E6&'7805'!F6))>0),1,0) | E380: =IF(D380=1,MAX(E$1:E379)+1,"") | F380: =IF(D380=1,IFERROR(CHOOSE(MATCH("X",'7805'!G6:L6,0),"①","②","③","④","⑤","⑥"),""),"") | G380: =IF(D380=1,IF('7805'!B6="","",'7805'!B6),"") | H380: =IF(D380=1,'7805'!N6&"","") | I380: =IF(D380=1,'7805'!C6&"","") | J380: =IF(D380=1,'7805'!E6&"","") | K380: =IF(D380=1,'7805'!D6&"","") | L380: =IF(D380=1,IF('7805'!F6="","",'7805'!F6),"")
A381: 7805 – Cultivating Professional Capacity | B381: 7805 | C381: 7 | D381: =IF(AND(UPPER(TRIM('7805'!A7))="CHOICE",LEN(TRIM('7805'!E7&'7805'!F7))>0),1,0) | E381: =IF(D381=1,MAX(E$1:E380)+1,"") | F381: =IF(D381=1,IFERROR(CHOOSE(MATCH("X",'7805'!G7:L7,0),"①","②","③","④","⑤","⑥"),""),"") | G381: =IF(D381=1,IF('7805'!B7="","",'7805'!B7),"") | H381: =IF(D381=1,'7805'!N7&"","") | I381: =IF(D381=1,'7805'!C7&"","") | J381: =IF(D381=1,'7805'!E7&"","") | K381: =IF(D381=1,'7805'!D7&"","") | L381: =IF(D381=1,IF('7805'!F7="","",'7805'!F7),"")
A382: 7805 – Cultivating Professional Capacity | B382: 7805 | C382: 8 | D382: =IF(AND(UPPER(TRIM('7805'!A8))="CHOICE",LEN(TRIM('7805'!E8&'7805'!F8))>0),1,0) | E382: =IF(D382=1,MAX(E$1:E381)+1,"") | F382: =IF(D382=1,IFERROR(CHOOSE(MATCH("X",'7805'!G8:L8,0),"①","②","③","④","⑤","⑥"),""),"") | G382: =IF(D382=1,IF('7805'!B8="","",'7805'!B8),"") | H382: =IF(D382=1,'7805'!N8&"","") | I382: =IF(D382=1,'7805'!C8&"","") | J382: =IF(D382=1,'7805'!E8&"","") | K382: =IF(D382=1,'7805'!D8&"","") | L382: =IF(D382=1,IF('7805'!F8="","",'7805'!F8),"")
A383: 7805 – Cultivating Professional Capacity | B383: 7805 | C383: 9 | D383: =IF(AND(UPPER(TRIM('7805'!A9))="CHOICE",LEN(TRIM('7805'!E9&'7805'!F9))>0),1,0) | E383: =IF(D383=1,MAX(E$1:E382)+1,"") | F383: =IF(D383=1,IFERROR(CHOOSE(MATCH("X",'7805'!G9:L9,0),"①","②","③","④","⑤","⑥"),""),"") | G383: =IF(D383=1,IF('7805'!B9="","",'7805'!B9),"") | H383: =IF(D383=1,'7805'!N9&"","") | I383: =IF(D383=1,'7805'!C9&"","") | J383: =IF(D383=1,'7805'!E9&"","") | K383: =IF(D383=1,'7805'!D9&"","") | L383: =IF(D383=1,IF('7805'!F9="","",'7805'!F9),"")
A384: 7805 – Cultivating Professional Capacity | B384: 7805 | C384: 10 | D384: =IF(AND(UPPER(TRIM('7805'!A10))="CHOICE",LEN(TRIM('7805'!E10&'7805'!F10))>0),1,0) | E384: =IF(D384=1,MAX(E$1:E383)+1,"") | F384: =IF(D384=1,IFERROR(CHOOSE(MATCH("X",'7805'!G10:L10,0),"①","②","③","④","⑤","⑥"),""),"") | G384: =IF(D384=1,IF('7805'!B10="","",'7805'!B10),"") | H384: =IF(D384=1,'7805'!N10&"","") | I384: =IF(D384=1,'7805'!C10&"","") | J384: =IF(D384=1,'7805'!E10&"","") | K384: =IF(D384=1,'7805'!D10&"","") | L384: =IF(D384=1,IF('7805'!F10="","",'7805'!F10),"")
A385: 7805 – Cultivating Professional Capacity | B385: 7805 | C385: 11 | D385: =IF(AND(UPPER(TRIM('7805'!A11))="CHOICE",LEN(TRIM('7805'!E11&'7805'!F11))>0),1,0) | E385: =IF(D385=1,MAX(E$1:E384)+1,"") | F385: =IF(D385=1,IFERROR(CHOOSE(MATCH("X",'7805'!G11:L11,0),"①","②","③","④","⑤","⑥"),""),"") | G385: =IF(D385=1,IF('7805'!B11="","",'7805'!B11),"") | H385: =IF(D385=1,'7805'!N11&"","") | I385: =IF(D385=1,'7805'!C11&"","") | J385: =IF(D385=1,'7805'!E11&"","") | K385: =IF(D385=1,'7805'!D11&"","") | L385: =IF(D385=1,IF('7805'!F11="","",'7805'!F11),"")
A386: 7805 – Cultivating Professional Capacity | B386: 7805 | C386: 12 | D386: =IF(AND(UPPER(TRIM('7805'!A12))="CHOICE",LEN(TRIM('7805'!E12&'7805'!F12))>0),1,0) | E386: =IF(D386=1,MAX(E$1:E385)+1,"") | F386: =IF(D386=1,IFERROR(CHOOSE(MATCH("X",'7805'!G12:L12,0),"①","②","③","④","⑤","⑥"),""),"") | G386: =IF(D386=1,IF('7805'!B12="","",'7805'!B12),"") | H386: =IF(D386=1,'7805'!N12&"","") | I386: =IF(D386=1,'7805'!C12&"","") | J386: =IF(D386=1,'7805'!E12&"","") | K386: =IF(D386=1,'7805'!D12&"","") | L386: =IF(D386=1,IF('7805'!F12="","",'7805'!F12),"")
A387: 7805 – Cultivating Professional Capacity | B387: 7805 | C387: 13 | D387: =IF(AND(UPPER(TRIM('7805'!A13))="CHOICE",LEN(TRIM('7805'!E13&'7805'!F13))>0),1,0) | E387: =IF(D387=1,MAX(E$1:E386)+1,"") | F387: =IF(D387=1,IFERROR(CHOOSE(MATCH("X",'7805'!G13:L13,0),"①","②","③","④","⑤","⑥"),""),"") | G387: =IF(D387=1,IF('7805'!B13="","",'7805'!B13),"") | H387: =IF(D387=1,'7805'!N13&"","") | I387: =IF(D387=1,'7805'!C13&"","") | J387: =IF(D387=1,'7805'!E13&"","") | K387: =IF(D387=1,'7805'!D13&"","") | L387: =IF(D387=1,IF('7805'!F13="","",'7805'!F13),"")
...
